[{"url": "https://www.douyin.com/hot/2074431", "title": "美国：中国大量取消美猪肉订单"}, {"url": "https://www.douyin.com/hot/2074230", "title": "媒体：电商平台向良性竞争回归"}, {"url": "https://www.douyin.com/hot/2074381", "title": "以旧换新带动销售额超7200亿"}, {"url": "https://www.douyin.com/hot/2073857", "title": "艾伦正式拜师老饭骨"}, {"url": "https://www.douyin.com/hot/2073687", "title": "王者版山海经"}, {"url": "https://www.douyin.com/hot/2074286", "title": "印巴局势为何突然升级"}, {"url": "https://www.douyin.com/hot/2073911", "title": "印媒称印巴发生小规模交火"}, {"url": "https://www.douyin.com/hot/2074465", "title": "云南玉昆2:3上海海港"}, {"url": "https://www.douyin.com/hot/2074536", "title": "郑钦文止步马德里站第二轮"}, {"url": "https://www.douyin.com/hot/2073530", "title": "周杰伦说演唱会多了专辑出不来"}, {"url": "https://www.douyin.com/hot/2074241", "title": "副部级宋朝华被查"}, {"url": "https://www.douyin.com/hot/2073584", "title": "当我瞒着家人考上了北大"}, {"url": "https://www.douyin.com/hot/2073760", "title": "夏天穿出红人搭配高级感"}, {"url": "https://www.douyin.com/hot/2074281", "title": "英媒：俄一高级军官被炸身亡"}, {"url": "https://www.douyin.com/hot/2073794", "title": "曝美防长办公电脑上装聊天应用"}, {"url": "https://www.douyin.com/hot/2073589", "title": "一种很新的东北森林"}, {"url": "https://www.douyin.com/hot/2073692", "title": "解锁夏日街头穿搭新思路"}, {"url": "https://www.douyin.com/hot/2074510", "title": "原神5.6版本前瞻"}, {"url": "https://www.douyin.com/hot/2074080", "title": "火影手游漂泊带土实战测评"}, {"url": "https://www.douyin.com/hot/2074181", "title": "小伙骑行可可西里遇到野狼"}, {"url": "https://www.douyin.com/hot/2073764", "title": "泰国警方一飞机坠毁致6死"}, {"url": "https://www.douyin.com/hot/2074173", "title": "内马尔的独白"}, {"url": "https://www.douyin.com/hot/2073767", "title": "林高远退出欧洲杯比赛"}, {"url": "https://www.douyin.com/hot/2073972", "title": "跳楼机原唱综艺首秀"}, {"url": "https://www.douyin.com/hot/2072674", "title": "AI为何会对你撒谎"}, {"url": "https://www.douyin.com/hot/2074011", "title": "街球霸王南昌站"}, {"url": "https://www.douyin.com/hot/2073907", "title": "迅猛龙考上复旦MBA了"}, {"url": "https://www.douyin.com/hot/2073957", "title": "谭维维王赫野土坡上的狗尾草"}, {"url": "https://www.douyin.com/hot/2074501", "title": "NBA季后赛强度有多可怕"}, {"url": "https://www.douyin.com/hot/2074156", "title": "孙俪胡曼黎1招制服无赖亲戚"}, {"url": "https://www.douyin.com/hot/2074152", "title": "快船新主场季后赛首胜"}, {"url": "https://www.douyin.com/hot/2073936", "title": "刘宇宁姚晓棠合唱座位有多痛"}, {"url": "https://www.douyin.com/hot/2073639", "title": "哈登连续单点约基奇"}, {"url": "https://www.douyin.com/hot/2074113", "title": "我的天降男友"}, {"url": "https://www.douyin.com/hot/2073065", "title": "你都用什么方式来纪念青春"}, {"url": "https://www.douyin.com/hot/2073877", "title": "沧元图2姬元宝消散名场面"}, {"url": "https://www.douyin.com/hot/2073736", "title": "这口心动我先吃了"}, {"url": "https://www.douyin.com/hot/2073859", "title": "李沁在抖音里成了新晋掌公主"}, {"url": "https://www.douyin.com/hot/2073802", "title": "谢霆锋含泪再唱与王菲定情曲"}, {"url": "https://www.douyin.com/hot/2073918", "title": "王源张碧晨合唱遇见"}, {"url": "https://www.douyin.com/hot/2074417", "title": "陈赫也被gogogo洗脑了"}, {"url": "https://www.douyin.com/hot/2074233", "title": "吵架有了专属bgm"}, {"url": "https://www.douyin.com/hot/2074405", "title": "李宗恒开门红首播和百乔烧烤局"}, {"url": "https://www.douyin.com/hot/2073105", "title": "请你忘掉我的模样反差转场"}, {"url": "https://www.douyin.com/hot/2073684", "title": "俄方：准备与美就乌问题达成协议"}, {"url": "https://www.douyin.com/hot/2074325", "title": "任嘉伦黑豹血脉觉醒杀疯了"}, {"url": "https://www.douyin.com/hot/2073139", "title": "歌词恨你恨你背景音却是想你"}, {"url": "https://www.douyin.com/hot/2074138", "title": "测评一下秋葵泡水"}, {"url": "https://www.douyin.com/hot/2074282", "title": "从菜市场走向山取展他用了60年"}, {"url": "https://www.douyin.com/hot/2074121", "title": "第五人格演绎之星投票"}, {"url": "https://www.douyin.com/hot/2074029", "title": "外交部回应美坚称中美正谈判"}, {"url": "https://www.douyin.com/hot/2074302", "title": "业内：李嘉诚卖港口只剩四种选择"}, {"url": "https://www.douyin.com/hot/2074342", "title": "13分钟看丧尸街背后的费城"}, {"url": "https://www.douyin.com/hot/2073437", "title": "如何看待特朗普考虑降低对华关税"}, {"url": "https://www.douyin.com/hot/2074094", "title": "张杰鸟巢演唱会第二周"}, {"url": "https://www.douyin.com/hot/2073808", "title": "上海车展迎来专业观众日"}, {"url": "https://www.douyin.com/hot/2073953", "title": "乌称基辅多地遭袭"}, {"url": "https://www.douyin.com/hot/2074234", "title": "直观感受中国基建有多厉害"}, {"url": "https://www.douyin.com/hot/2073445", "title": "无忧渡全员上桌"}, {"url": "https://www.douyin.com/hot/2074398", "title": "辽宁锦州一职校发生刑事案件"}, {"url": "https://www.douyin.com/hot/2073486", "title": "安徽铁塔就不雅视频致歉"}, {"url": "https://www.douyin.com/hot/2074160", "title": "快船如何迎回巅峰莱昂纳德"}, {"url": "https://www.douyin.com/hot/2073758", "title": "第16届金扫帚奖获奖名单"}, {"url": "https://www.douyin.com/hot/2073498", "title": "文班亚马踢足球"}, {"url": "https://www.douyin.com/hot/2074133", "title": "理发师晓华要给马丽剪头发"}, {"url": "https://www.douyin.com/hot/2073668", "title": "贾跃亭被正式任命为FF联席CEO"}, {"url": "https://www.douyin.com/hot/2074083", "title": "刘非任杭州市委书记"}, {"url": "https://www.douyin.com/hot/2073922", "title": "邓超把孙俪当豆包养"}, {"url": "https://www.douyin.com/hot/2072518", "title": "媒体评英国航母高调“重返印太”"}, {"url": "https://www.douyin.com/hot/2073667", "title": "莫兰特受伤离场"}, {"url": "https://www.douyin.com/hot/2073223", "title": "iG发布公告声明"}, {"url": "https://www.douyin.com/hot/2073536", "title": "特朗普罕见批评普京"}, {"url": "https://www.douyin.com/hot/2073623", "title": "淮水竹亭内娱真王炸阵容"}, {"url": "https://www.douyin.com/hot/2073088", "title": "孤单星球这下真孤单了"}, {"url": "https://www.douyin.com/hot/2073874", "title": "中共中央政治局召开会议"}, {"url": "https://www.douyin.com/hot/2072774", "title": "上海车展有人打架系谣言"}, {"url": "https://www.douyin.com/hot/2073628", "title": "猿辅导回应员工猝死"}, {"url": "https://www.douyin.com/hot/2072720", "title": "ootd的风也吹到了广场舞"}, {"url": "https://www.douyin.com/hot/2073285", "title": "无尽的尽头冲击力好大"}, {"url": "https://www.douyin.com/hot/2073803", "title": "北京体育大学校运会太燃了"}, {"url": "https://www.douyin.com/hot/2072759", "title": "合着把门关上训的是我们"}, {"url": "https://www.douyin.com/hot/2073619", "title": "榜上佳婿今日开播"}, {"url": "https://www.douyin.com/hot/2073533", "title": "萌宠版请你忘掉我的模样"}, {"url": "https://www.douyin.com/hot/2073092", "title": "秀莲偶遇少安了"}, {"url": "https://www.douyin.com/hot/2072041", "title": "孤单星球转了多久"}, {"url": "https://www.douyin.com/hot/2072972", "title": "新疆下井救人00后女辅警破格晋升"}, {"url": "https://www.douyin.com/hot/2073798", "title": "成毅谈漫改感受"}, {"url": "https://www.douyin.com/hot/2073731", "title": "中国航天史上第6次太空会师"}, {"url": "https://www.douyin.com/hot/2073921", "title": "沃尔玛等零售商警告特朗普"}, {"url": "https://www.douyin.com/hot/2073067", "title": "奥沙利文：两年内不参加表演赛"}, {"url": "https://www.douyin.com/hot/2073426", "title": "直击上海车展：车企不提“智驾”了"}, {"url": "https://www.douyin.com/hot/2072320", "title": "曹骏 古早白月光绝杀"}, {"url": "https://www.douyin.com/hot/2072994", "title": "广厦队赵嘉仁赛季报销"}, {"url": "https://www.douyin.com/hot/2072975", "title": "仰望U8L对比极氪9X"}, {"url": "https://www.douyin.com/hot/2073209", "title": "特朗普的态度为何出现变化"}, {"url": "https://www.douyin.com/hot/2073330", "title": "深圳暴雨"}, {"url": "https://www.douyin.com/hot/2072977", "title": "任嘉伦在我抖音摇了3天了"}, {"url": "https://www.douyin.com/hot/2073306", "title": "你就是我的风景"}, {"url": "https://www.douyin.com/hot/2073413", "title": "巴方要求印度就恐袭指控举证"}, {"url": "https://www.douyin.com/hot/2072861", "title": "董宇辉麦家说故乡就像胎记"}, {"url": "https://www.douyin.com/hot/2073710", "title": "梁王组合展望苏迪曼杯"}, {"url": "https://www.douyin.com/hot/2072920", "title": "神二十与太阳同框瞬间"}, {"url": "https://www.douyin.com/hot/2073062", "title": "两代奥运冠军为神二十送祝福"}, {"url": "https://www.douyin.com/hot/2072875", "title": "阿门：我是无意撞倒巴特勒"}, {"url": "https://www.douyin.com/hot/2073700", "title": "暗区端游表演赛天禄vs绿龙"}, {"url": "https://www.douyin.com/hot/2073432", "title": "莫布里赛季最佳防守球员"}, {"url": "https://www.douyin.com/hot/2073732", "title": "半夏说和宣夜的女儿是小豹子"}, {"url": "https://www.douyin.com/hot/2073522", "title": "这一刻他是全班的“英雄”"}, {"url": "https://www.douyin.com/hot/2073283", "title": "随时随地节奏感训练"}, {"url": "https://www.douyin.com/hot/2073745", "title": "江辰好像知道他很帅"}, {"url": "https://www.douyin.com/hot/2072719", "title": "已经到了对零食毫无欲望的年纪了"}, {"url": "https://www.douyin.com/hot/2073637", "title": "RED新专先行曲"}, {"url": "https://www.douyin.com/hot/2073141", "title": "这两天印度巴基斯坦发生了什么"}, {"url": "https://www.douyin.com/hot/2072770", "title": "商务部回应中美关税降温说法"}, {"url": "https://www.douyin.com/hot/2072499", "title": "揭秘神二十出征地东风航天城"}, {"url": "https://www.douyin.com/hot/2072743", "title": "赵露思金色小短裙"}, {"url": "https://www.douyin.com/hot/2072716", "title": "商务部召开外资企业圆桌会"}, {"url": "https://www.douyin.com/hot/2071966", "title": "神二十发射有哪些看点"}, {"url": "https://www.douyin.com/hot/2073110", "title": "小红书拟取消大小周引热议"}, {"url": "https://www.douyin.com/hot/2072669", "title": "健康的100种公式"}, {"url": "https://www.douyin.com/hot/2072519", "title": "刘涛近一周涨粉超百万"}, {"url": "https://www.douyin.com/hot/2072278", "title": "当86岁的爷爷摆摊写婚书"}, {"url": "https://www.douyin.com/hot/2073103", "title": "高校运动会开幕式有多燃"}, {"url": "https://www.douyin.com/hot/2073431", "title": "尼克斯118:116险胜活塞"}, {"url": "https://www.douyin.com/hot/2072654", "title": "曝iPhone 17关键材料短缺"}, {"url": "https://www.douyin.com/hot/2073273", "title": "无忧渡半夏早就知道宣夜是妖"}, {"url": "https://www.douyin.com/hot/2071490", "title": "美好的爱情是什么样子"}, {"url": "https://www.douyin.com/hot/2071458", "title": "练了多年的功夫今天用上了"}, {"url": "https://www.douyin.com/hot/2072951", "title": "100秒回顾神二十发射全程"}, {"url": "https://www.douyin.com/hot/2072553", "title": "韩国回应“在中美之间二选一”"}, {"url": "https://www.douyin.com/hot/2073015", "title": "广州暴雨"}, {"url": "https://www.douyin.com/hot/2073388", "title": "神二十与空间站完成对接"}, {"url": "https://www.douyin.com/hot/2072531", "title": "媒体：Uzi大概率入选名人堂"}, {"url": "https://www.douyin.com/hot/2072280", "title": "神舟二十号发射圆满成功"}, {"url": "https://www.douyin.com/hot/2072758", "title": "外交部否认中美就关税问题谈判"}, {"url": "https://www.douyin.com/hot/2073677", "title": "部分企业称从美进口半导体免加征关税"}, {"url": "https://www.douyin.com/hot/2072532", "title": "阿尔特塔：不想用欧冠当借口"}, {"url": "https://www.douyin.com/hot/2072483", "title": "民众排长龙瞻仰教宗方济各遗体"}, {"url": "https://www.douyin.com/hot/2072493", "title": "无尽的尽头开播高能反霸凌"}, {"url": "https://www.douyin.com/hot/2073389", "title": "神十九神二十航天员会师"}, {"url": "https://www.douyin.com/hot/2073313", "title": "特朗普又跟泽连斯基刚上了"}, {"url": "https://www.douyin.com/hot/2072706", "title": "曹骏无忧渡三界跑酷"}, {"url": "https://www.douyin.com/hot/2072957", "title": "杨坤回应起诉模仿者“四川芬达”"}, {"url": "https://www.douyin.com/hot/2072793", "title": "东部战区回应美舰过航台湾海峡"}, {"url": "https://www.douyin.com/hot/2072651", "title": "美食是旅行的起点"}, {"url": "https://www.douyin.com/hot/2073084", "title": "小奇摇挑战"}, {"url": "https://www.douyin.com/hot/2073365", "title": "陈丽君 说不完的宝玉一生"}, {"url": "https://www.douyin.com/hot/2072477", "title": "火勇对飚三分"}, {"url": "https://www.douyin.com/hot/2073109", "title": "塞尔比世锦赛霸气清台"}, {"url": "https://www.douyin.com/hot/2072689", "title": "光遇青鸟季攻略"}, {"url": "https://www.douyin.com/hot/2072490", "title": "沉浸式板书"}, {"url": "https://www.douyin.com/hot/2073107", "title": "林树直播破纪录喊陈赫上五哈"}, {"url": "https://www.douyin.com/hot/2072782", "title": "国防部回应航母对外开放"}, {"url": "https://www.douyin.com/hot/2072318", "title": "河南连续3天有厅官落马"}, {"url": "https://www.douyin.com/hot/2072243", "title": "奥沙利文轻取卡特晋级16强"}, {"url": "https://www.douyin.com/hot/2072292", "title": "王者三分之地新英雄即将上线"}, {"url": "https://www.douyin.com/hot/2072330", "title": "波音证实中国拒收50架新订购飞机"}, {"url": "https://www.douyin.com/hot/2072221", "title": "绍伊古喊话美国"}, {"url": "https://www.douyin.com/hot/2072832", "title": "国防部回应台军爆发离职潮"}, {"url": "https://www.douyin.com/hot/2073008", "title": "孙坚在国外3天被偷2次"}, {"url": "https://www.douyin.com/hot/2072431", "title": "45岁谢霆锋时隔20年开演唱会"}, {"url": "https://www.douyin.com/hot/2072691", "title": "赖清德所在办公楼失火"}, {"url": "https://www.douyin.com/hot/2072517", "title": "打破“社会时钟”的人生"}, {"url": "https://www.douyin.com/hot/2072968", "title": "王者三丽鸥结算页面"}, {"url": "https://www.douyin.com/hot/2072505", "title": "三角洲猛攻节预热开启"}, {"url": "https://www.douyin.com/hot/2071580", "title": "媒体评聋哑女生宸玥走红"}, {"url": "https://www.douyin.com/hot/2072347", "title": "第一视角体验维修师傅的一天"}, {"url": "https://www.douyin.com/hot/2072236", "title": "日本推广液体鸡蛋"}, {"url": "https://www.douyin.com/hot/2072367", "title": "一口气看完上海车展"}, {"url": "https://www.douyin.com/hot/2072366", "title": "巴特勒倒地受伤提前离场"}, {"url": "https://www.douyin.com/hot/2072237", "title": "金价跌了还能买吗"}, {"url": "https://www.douyin.com/hot/2071588", "title": "专家：消费者薅羊毛成过去式"}, {"url": "https://www.douyin.com/hot/2072203", "title": "我们的友谊纪念日"}, {"url": "https://www.douyin.com/hot/2072445", "title": "深圳水贝商家称金条已断货"}, {"url": "https://www.douyin.com/hot/2072668", "title": "李星云降臣对决拔里神玉"}, {"url": "https://www.douyin.com/hot/2072364", "title": "张继科说王励勤训练从不迟到"}, {"url": "https://www.douyin.com/hot/2071988", "title": "回忆成了大问题反差转场"}, {"url": "https://www.douyin.com/hot/2072615", "title": "佳诺摇舞蹈挑战"}, {"url": "https://www.douyin.com/hot/2073259", "title": "央行将开展6000亿元MLF操作"}, {"url": "https://www.douyin.com/hot/2072128", "title": "赵露思回到2018"}, {"url": "https://www.douyin.com/hot/2073176", "title": "小米员工称平均工时12小时被约谈"}, {"url": "https://www.douyin.com/hot/2071935", "title": "灵魂摆渡十年了"}, {"url": "https://www.douyin.com/hot/2072781", "title": "邓超在家喊胡曼黎被孙俪骂"}, {"url": "https://www.douyin.com/hot/2072457", "title": "秀鞋的一百种方式"}]