[{"url": "https://www.douyin.com/hot/2563628", "title": "从空间站俯瞰台风巴威有多大"}, {"url": "https://www.douyin.com/hot/2562882", "title": "万物皆可波点风"}, {"url": "https://www.douyin.com/hot/2563823", "title": "我国人工智能产业加速发展壮大"}, {"url": "https://www.douyin.com/hot/2563858", "title": "直击洪水洪峰过境"}, {"url": "https://www.douyin.com/hot/2562965", "title": "17级台风威力有多大"}, {"url": "https://www.douyin.com/hot/2562111", "title": "小个子的夏日氛围感穿搭"}, {"url": "https://www.douyin.com/hot/2563867", "title": "中国U17男足不敌坦桑尼亚"}, {"url": "https://www.douyin.com/hot/2563058", "title": "UFC上海站宋亚东将对阵乌马尔"}, {"url": "https://www.douyin.com/hot/2562712", "title": "美军时隔10天再袭伊朗"}, {"url": "https://www.douyin.com/hot/2562637", "title": "台风巴威未来趋势和影响"}, {"url": "https://www.douyin.com/hot/2563084", "title": "骁唤醒了我的江湖病"}, {"url": "https://www.douyin.com/hot/2563376", "title": "凡人修仙传大晋实力有多强"}, {"url": "https://www.douyin.com/hot/2563257", "title": "埃及总统发声"}, {"url": "https://www.douyin.com/hot/2563772", "title": "广西百色辟谣网传严重洪灾视频"}, {"url": "https://www.douyin.com/hot/2563228", "title": "和我吃饭从不A钱之人"}, {"url": "https://www.douyin.com/hot/2563369", "title": "功夫女足发声明抵制倒卖门票"}, {"url": "https://www.douyin.com/hot/2563153", "title": "慢充旅行太治愈了"}, {"url": "https://www.douyin.com/hot/2563741", "title": "当阿根廷球迷上了埃及司机的车"}, {"url": "https://www.douyin.com/hot/2563280", "title": "G2 3:1战胜T1"}, {"url": "https://www.douyin.com/hot/2563688", "title": "抖音网友善意正送往广西灾区"}, {"url": "https://www.douyin.com/hot/2563702", "title": "哈兰德名场面评选大会"}, {"url": "https://www.douyin.com/hot/2563699", "title": "徐明浩这个舞我能跳"}, {"url": "https://www.douyin.com/hot/2563243", "title": "用特效回到2018年的夏天"}, {"url": "https://www.douyin.com/hot/2563231", "title": "密室四怂组队能吵吵绝不动腿"}, {"url": "https://www.douyin.com/hot/2562944", "title": "OMG你香到我啦"}, {"url": "https://www.douyin.com/hot/2562741", "title": "阿根廷对阵埃及判罚争议"}, {"url": "https://www.douyin.com/hot/2562315", "title": "知道你不能还要你感受"}, {"url": "https://www.douyin.com/hot/2563200", "title": "无限流鼻祖恐怖游轮定档"}, {"url": "https://www.douyin.com/hot/2562058", "title": "妈生感乖乖脸是特效给的"}, {"url": "https://www.douyin.com/hot/2561735", "title": "管泽元再现姆巴佩之剑吟唱"}, {"url": "https://www.douyin.com/hot/2563250", "title": "谁懂涂鸦耳机的ins感"}, {"url": "https://www.douyin.com/hot/2562866", "title": "我的大学生三下乡日记"}, {"url": "https://www.douyin.com/hot/2562997", "title": "和雷霆美食ride or die"}, {"url": "https://www.douyin.com/hot/2563812", "title": "何洁聂小倩蝴蝶杀花妆绝了"}, {"url": "https://www.douyin.com/hot/2563903", "title": "CHIQUITA跳舞爽到我了"}, {"url": "https://www.douyin.com/hot/2563517", "title": "亚当刘柏辛歌手节目后再合作新歌"}, {"url": "https://www.douyin.com/hot/2563215", "title": "我最最最爱的你"}, {"url": "https://www.douyin.com/hot/2563142", "title": "功夫女足心中那团火跳起来了"}, {"url": "https://www.douyin.com/hot/2562961", "title": "陈异苗靖废墟初吻"}, {"url": "https://www.douyin.com/hot/2562957", "title": "这个暑假我先吃为敬"}, {"url": "https://www.douyin.com/hot/2562611", "title": "苗靖想喝的海带绿豆汤是什么"}, {"url": "https://www.douyin.com/hot/2561566", "title": "是谁的呼唤叫醒了沉睡的我"}, {"url": "https://www.douyin.com/hot/2562801", "title": "带你第一视角体验溪降"}, {"url": "https://www.douyin.com/hot/2562312", "title": "多少年以后往事随云走"}, {"url": "https://www.douyin.com/hot/2563117", "title": "蓝战非探访亚速尔群岛"}, {"url": "https://www.douyin.com/hot/2562142", "title": "欢迎收听来自DJosama的音乐"}, {"url": "https://www.douyin.com/hot/2563598", "title": "来中山就为了这口乳鸽宴"}, {"url": "https://www.douyin.com/hot/2563701", "title": "就爱雷童这个又争又抢"}, {"url": "https://www.douyin.com/hot/2563469", "title": "株洲菜从来没让我失望过"}, {"url": "https://www.douyin.com/hot/2562261", "title": "和嘉之派一起做潮汕卤鹅掌"}, {"url": "https://www.douyin.com/hot/2562640", "title": "深度解读台风巴威为什么这么强"}, {"url": "https://www.douyin.com/hot/2563350", "title": "张真源密室拥抱NPC第一人"}, {"url": "https://www.douyin.com/hot/2562300", "title": "大家好今天我快被热化了"}, {"url": "https://www.douyin.com/hot/2563100", "title": "徐良伴舞小哥这次跳了GIRLS"}, {"url": "https://www.douyin.com/hot/2562626", "title": "当代年轻人反向省钱实录"}]