[{"url": "https://b23.tv/BV1ki42117tH", "title": "《大学生流浪小技巧》"}, {"url": "https://b23.tv/BV12f421S76R", "title": "六年捡漏，倒反天罡"}, {"url": "https://b23.tv/BV17T42197XN", "title": "最 强 嘴 替"}, {"url": "https://b23.tv/BV13Z421E7Ce", "title": "大型纪录片之《漫展显眼包》"}, {"url": "https://b23.tv/BV1wz421U7LZ", "title": "《崩坏：星穹铁道》千星纪游PV：「假若有一双翅膀」"}, {"url": "https://b23.tv/BV1Lr421J7js", "title": "四菜一汤教程"}, {"url": "https://b23.tv/BV1Pt421F78Y", "title": "自制多功能电动拐仗"}, {"url": "https://b23.tv/BV1LZ421E7mS", "title": "看完4月新番，我无地自容！羞愧难当！【泛式】"}, {"url": "https://b23.tv/BV1Xx4y1B7Kn", "title": "疑 难 门 诊 ⑥——“朋友，你想杀了我吗”"}, {"url": "https://b23.tv/BV1Yr42137MC", "title": "请小潮院长爸爸吃饭！"}, {"url": "https://b23.tv/BV1Rb421h7zb", "title": "当低情商朋友来到家里遇到低情商老妈"}, {"url": "https://b23.tv/BV14m421H7DB", "title": "当我们把身体器官换成了「龙的器官」脆骨症第二期！！"}, {"url": "https://b23.tv/BV1pz421D7iy", "title": "【闹腾男孩KC】可你不是当过小孩了吗"}, {"url": "https://b23.tv/BV1nm41117cs", "title": "《大魔术师》：揭秘这场愚弄人心的把戏"}, {"url": "https://b23.tv/BV1ZC411E7fz", "title": "射 击 专 项 训 练"}, {"url": "https://b23.tv/BV1nw4m1y7zd", "title": "《慢冷》空拍？心跳也漏半拍｜马嘉祺深情弹唱诠释破碎浪漫·时代少年团楼间楼演唱会"}, {"url": "https://b23.tv/BV1uz421U7RR", "title": "出声就死"}, {"url": "https://b23.tv/BV11i42117g7", "title": "100人公司转椅逃亡赛，胜者瓜分5万元！影视飓风破产团建4.0"}, {"url": "https://b23.tv/BV1SC411775K", "title": "⚡️仆 芙 双 摇⚡️Queencard！【咬人猫x咬人喵】"}, {"url": "https://b23.tv/BV1TJ4m1E7hd", "title": "“全家”桶"}, {"url": "https://b23.tv/BV18z421U7qm", "title": "《药圣周杰伦》"}, {"url": "https://b23.tv/BV1aC411J7rB", "title": "人工智能的尽头是人工"}, {"url": "https://b23.tv/BV1ZE421V7fU", "title": "大家快来玩这种“很新”的植物大战僵尸，就是有点费人"}, {"url": "https://b23.tv/BV1em421p7CF", "title": "朋友，我们已经渐行渐远了"}, {"url": "https://b23.tv/BV1if421S7do", "title": "⿰字见 / Zixian"}, {"url": "https://b23.tv/BV1tT42197fe", "title": "教室"}, {"url": "https://b23.tv/BV1et421c76b", "title": "马上要一百万粉丝了！"}, {"url": "https://b23.tv/BV1Tb421e7hC", "title": "《明日方舟》EP - Echoism"}, {"url": "https://b23.tv/BV1GJ4m1J7gz", "title": "爽片成真？失去女儿的母亲，独自报复整个黑帮"}, {"url": "https://b23.tv/BV1AD421K7Ha", "title": "华晨宇看日出演唱会15分钟《向阳而生》（日出live版）"}, {"url": "https://b23.tv/BV1mZ421J7gv", "title": "出来吧！五金圣剑！"}, {"url": "https://b23.tv/BV1yb42187sh", "title": "这次是真教学！学会这套眼神，再也不怕吵架吵不过了！！"}, {"url": "https://b23.tv/BV1bJ4m1K7Wi", "title": "【星铁嘉年华】你能抵挡全角色COSER向你走来的魅力吗？【4K60P】"}, {"url": "https://b23.tv/BV1Nm421W7NC", "title": "我买了抗日战争的国产武器！90年的历史！中国近代首款制式武器！"}, {"url": "https://b23.tv/BV1fr421E7K1", "title": "老板让五一假期搞点动静出来！不知道这动静老板满意吗"}, {"url": "https://b23.tv/BV19r421u7af", "title": "【硬核】一口气了解黄金 | 为什么暴涨? 投资黄金需要注意什么?"}, {"url": "https://b23.tv/BV1eH4y137Hx", "title": "白手起家！我决定开一家超市！"}, {"url": "https://b23.tv/BV1SD421T7Sn", "title": "我收容了MC世界的所有珍稀生物！！！"}, {"url": "https://b23.tv/BV1dx4y1q7Gn", "title": "【宋亚轩】“你就是那唯一，我会永远爱你”宋亚轩深情演绎《蝴蝶》"}, {"url": "https://b23.tv/BV1WM4m1d7ps", "title": "我没听清！"}, {"url": "https://b23.tv/BV1gE421j7xM", "title": "Q宠大乐斗现状如何？一把武器居然要花几万块！"}, {"url": "https://b23.tv/BV15J4m1K76C", "title": "快叫你朋友来看倒霉蛋挑战"}, {"url": "https://b23.tv/BV1Lf421D7Ah", "title": "《cosplay是你的谎言》"}, {"url": "https://b23.tv/BV1HM4m1d7D4", "title": "这回青青草原到底是谁最强？？？"}, {"url": "https://b23.tv/BV1i142167Uy", "title": "豆瓣9.5！14年前火爆全国的神作【魔角侦探】大结局究竟是什么？"}, {"url": "https://b23.tv/BV1Hi421k7z8", "title": "看好了！一生只能使用一次的 白手起家β"}, {"url": "https://b23.tv/BV1eZ42177My", "title": "吃多了辣条就可以成为“辣”妹了吧🌶️🌶️🌶️"}, {"url": "https://b23.tv/BV1hz421U79V", "title": "下集家人们想看王妈还是继续当老师！"}, {"url": "https://b23.tv/BV17f421S7w7", "title": "也算是进到了cos圈哈哈"}, {"url": "https://b23.tv/BV1TD421M7gM", "title": "好好好，谁能有你聪明啊！一整个醍醐灌顶。"}, {"url": "https://b23.tv/BV1Tr421u7Xn", "title": "用爆款神曲《5:20AM》告诉你，什么是“辣条音乐”！【路哥锐评】"}, {"url": "https://b23.tv/BV16w4m1C7uN", "title": "我看到了中国唯一没有的地貌，峡湾地貌！"}, {"url": "https://b23.tv/BV1sx4y1B7MZ", "title": "【原神日常】#23  仆人：孩子的学校里面都是些什么奇怪的人啊…"}, {"url": "https://b23.tv/BV1Eb421a752", "title": "暗区真人剧【卡莫纳的故事】第四集：钥匙"}, {"url": "https://b23.tv/BV1KE42157Qp", "title": "【杜比视界】是建模还是实拍？它真的能骗过人眼！"}, {"url": "https://b23.tv/BV1yx4y1B7Jd", "title": "辣死啦~~~~~"}, {"url": "https://b23.tv/BV1DZ421J7GS", "title": "我用6个月在VR里画出世界名画《蒙娜丽莎》庆祝中法建交60周年"}, {"url": "https://b23.tv/BV1sT42197vY", "title": "拍了十二个小时的印度变装，我来晚了！"}, {"url": "https://b23.tv/BV1KC411E7nH", "title": "租房押金扣了我32万"}, {"url": "https://b23.tv/BV1Ms421K7ST", "title": "儿子哥：原来我刚刚这么恶心的吗"}, {"url": "https://b23.tv/BV1jm421W7RL", "title": "《鸣潮》共鸣者「凌阳」展示PV丨首次登演"}, {"url": "https://b23.tv/BV1hJ4m1K7Uu", "title": "这绝对是你看过的最像的霍尔海雅"}, {"url": "https://b23.tv/BV1Cz421U7Mh", "title": "阿姨好像嗑起来了"}, {"url": "https://b23.tv/BV1pT421X715", "title": "《SOS》"}, {"url": "https://b23.tv/BV1ND421M7eH", "title": "哥哥拍的：甜妹"}, {"url": "https://b23.tv/BV1Ri42117wS", "title": "我家没了！"}, {"url": "https://b23.tv/BV19i42117DZ", "title": "大型纪录片之《致命保安》为您奉上！"}, {"url": "https://b23.tv/BV1Mt421F7Fr", "title": "好了，以后没教室了，不更新了。"}, {"url": "https://b23.tv/BV1E142197XA", "title": "五星极品车模"}, {"url": "https://b23.tv/BV1vC411J75K", "title": "一口气看完动画版变态小说《十宗罪》20个真实事件改编的案件，一个比一个变态，可结局却值得反思！"}, {"url": "https://b23.tv/BV1Em421W7uQ", "title": "网络热门“智熄”视频鉴定（68）— 乌镇水底下的超级计算机"}, {"url": "https://b23.tv/BV1im41117vg", "title": "中国的方言有多美"}, {"url": "https://b23.tv/BV1yb421h7XY", "title": "新型漫展恶性事件，大家谨以为戒！保护自身安全！"}, {"url": "https://b23.tv/BV1Vm421H7dj", "title": "老板在厕所里半天我们员工都憋不住了咋画捏?"}, {"url": "https://b23.tv/BV1xw4m1X7EN", "title": "历时一年多，我居然真的用草莓上的籽种出了草莓！"}, {"url": "https://b23.tv/BV1MH4y1G7p3", "title": "这串泡泡含妈量极高"}, {"url": "https://b23.tv/BV1MC411n74M", "title": "坏了，看来他真的一心一意只为阿蕾奇诺…"}, {"url": "https://b23.tv/BV17D421K7EY", "title": "我的世界：真人脸识别器，只有自己能开的大门"}, {"url": "https://b23.tv/BV1KM4m1f7AN", "title": "【MrBeast官方】在圈里活100天赢得$500000美元！"}, {"url": "https://b23.tv/BV1UT421C7X1", "title": "仆人：美味的蓝莓小蛋糕！！〖白白剧场〗"}, {"url": "https://b23.tv/BV1fT421X7ZY", "title": "装修省钱小妙招，随便搜搜几万块钱就省下来了。#装修 #省钱攻略 #情侣 #源头工厂"}, {"url": "https://b23.tv/BV14Z421J7jZ", "title": "今天我要拍的演员是___"}, {"url": "https://b23.tv/BV19H4y1G7Lj", "title": "维也纳金色大厅蕉响乐演奏【大香蕉】绝世超燃！！！（迫真）"}, {"url": "https://b23.tv/BV1CH4y137fY", "title": "恶魔轮盘 M C 版！但「吃蛋糕」就会...？"}, {"url": "https://b23.tv/BV1Vw4m1y7LS", "title": "狗：我进化了！"}, {"url": "https://b23.tv/BV1rr421E7uY", "title": "【狛枝凪斗/生贺动画】日向，你知道谁是凶手吗？"}, {"url": "https://b23.tv/BV1xC411J7vP", "title": "卵胞浆内单精子显微注射技术ICSI (Intracytoplasmic sperm injection)"}, {"url": "https://b23.tv/BV15C411J7uV", "title": "mc 但是「专家级难度」？？！"}, {"url": "https://b23.tv/BV1QD421N7ur", "title": "学会广西步，明天滑去广西住"}, {"url": "https://b23.tv/BV1Tb421e7oL", "title": "内心丰盈者，独行也如众"}, {"url": "https://b23.tv/BV1PD421T7mc", "title": "金字塔塔尖95成新，女生自用可小刀"}, {"url": "https://b23.tv/BV1bm411C7oW", "title": "“你知道哥哥我有多努力吗”"}, {"url": "https://b23.tv/BV1xT421C77L", "title": "孙燕姿的情歌是一座失恋博物馆丨HOPICO"}, {"url": "https://b23.tv/BV1gZ421J7HS", "title": "鉴定咬伤粉丝的毒蛇(9)网友被毒蛇咬伤！竟然拿网图来找龙雅鉴定？连伤口都是假的？"}, {"url": "https://b23.tv/BV12C411J7d7", "title": "亲嘴的不抓，抓玩希沃白板的？"}, {"url": "https://b23.tv/BV1DH4y1V7Pi", "title": "《装杯同事》"}, {"url": "https://b23.tv/BV12b421a7yv", "title": "糟糕！我被星铁land的coser们嫌弃了"}, {"url": "https://b23.tv/BV1Jf421S73m", "title": "探秘中国最神秘餐厅！北京皇家园林，御膳房牛排馆！"}, {"url": "https://b23.tv/BV1Vs421K7EM", "title": "重开150次！挑战无伤通关《无敌流浪汉》！？"}, {"url": "https://b23.tv/BV19m421s7kn", "title": "三体人害怕林黛玉"}, {"url": "https://b23.tv/BV1aD421T73i", "title": "就有一种想上去问他“今年多大啦？”的冲动"}, {"url": "https://b23.tv/BV1xE421j7Uv", "title": "【硬核科普】从零开始认识显卡"}, {"url": "https://b23.tv/BV1ZE421L7rV", "title": "《 天 价 水 果 》第八期"}, {"url": "https://b23.tv/BV1uM4m1d7x6", "title": "前几天没更新 出了趟门"}, {"url": "https://b23.tv/BV1Tz421D7qG", "title": "这个视频有你朋友的影子吗？"}, {"url": "https://b23.tv/BV1R4421f7pc", "title": "是谁改了我的键位"}, {"url": "https://b23.tv/BV1Rb421h7Yi", "title": "慢性中毒"}, {"url": "https://b23.tv/BV19H4y1G7uu", "title": "当我发现教了学生的孩子"}, {"url": "https://b23.tv/BV1Zm421s76L", "title": "穿越到远古时代，结果开局就一堆霸王龙骑士？"}, {"url": "https://b23.tv/BV1Bi421C73a", "title": "别瞎想了，没一句暗示！"}]