[{"url": "https://b23.tv/BV1ub421J7vH", "title": "你说我打的是老板儿子？（狂喜）"}, {"url": "https://b23.tv/BV1dE4m1R7LG", "title": "七夕节老番茄想和自己玩游戏"}, {"url": "https://b23.tv/BV1DW421X7Wx", "title": "遗憾总是贯穿人生的始终"}, {"url": "https://b23.tv/BV1VE4m1d76e", "title": "《忍术回战》——前篇"}, {"url": "https://b23.tv/BV1yE4m1R7NY", "title": "再次逼疯小潮院长"}, {"url": "https://b23.tv/BV1BH4y1c7xo", "title": "《绝区零》青衣角色展示 | 青童与白叟"}, {"url": "https://b23.tv/BV1oH4y1c7Kk", "title": "《黑神话：悟空》最终预告 | 8月20日，重走西游"}, {"url": "https://b23.tv/BV1h1421t7A5", "title": "通缉令太丑，罪犯发来了自拍"}, {"url": "https://b23.tv/BV1SE421w7Di", "title": "【李不白磨针】视频已打包，欢迎围观！"}, {"url": "https://b23.tv/BV1gr421M73D", "title": "粪便侵染五成雪糕？春秋笔法切莫作妖！"}, {"url": "https://b23.tv/BV1Mm42137j3", "title": "究极无敌难狗生存!当你开局只有「3滴血」!!?丨MITE打破一切 第三期"}, {"url": "https://b23.tv/BV1hi421a7hk", "title": "这是不是校门口的你！"}, {"url": "https://b23.tv/BV1rf421q7JE", "title": "开胃小菜"}, {"url": "https://b23.tv/BV1WS42197sQ", "title": "“贝利亚，你给我等着！”"}, {"url": "https://b23.tv/BV17T42167sa", "title": "师徒之战！卡牌对决！特效小哥大战刘谦！"}, {"url": "https://b23.tv/BV1Wb421J7hA", "title": "🫅 浴 皇 大 帝"}, {"url": "https://b23.tv/BV1ff421q7V4", "title": "（  矛 断 了，但 还 有 盾  ）"}, {"url": "https://b23.tv/BV1xS42197Fv", "title": "【散人】国产民俗恐怖《纸嫁衣7》卿不负（P1.寻祭）"}, {"url": "https://b23.tv/BV11f421q7X1", "title": "老板pua你如何反驳"}, {"url": "https://b23.tv/BV14M4m1y7GD", "title": "恶心！互联网上最毁三观的视频！给我看吐了！孕妇也打擦边球？！"}, {"url": "https://b23.tv/BV1JS42197vz", "title": "Chris James - 已经被大家的热情融化啦！！！谢谢中国，我爱你们！！！！！"}, {"url": "https://b23.tv/BV152421Z7FF", "title": "年度爽文！被打后手把手教你拿到人生第一桶金！【被打后续 逐帧分析】"}, {"url": "https://b23.tv/BV1nE421w78A", "title": "浙 江 现 状"}, {"url": "https://b23.tv/BV1R4421U7rs", "title": "听劝❗这才是适合中国宝宝的俄罗斯旅行"}, {"url": "https://b23.tv/BV1gi421a7Qi", "title": "七夕佳节来喝蜜雪也是给你面子了！"}, {"url": "https://b23.tv/BV1PS421d7Ha", "title": "这些学生最应该知道的！可惜以前没人告诉我…最全学生时代信息渠道，校内资源/保研/考研/专升本/竞赛/考证/项目/体制内/企业实习就业"}, {"url": "https://b23.tv/BV1SU411U7rv", "title": "美国虚伪的“反兴奋剂”口号下，藏了多少违规黑幕？"}, {"url": "https://b23.tv/BV18142187Eh", "title": "我敢打赌，99%的人没有用过这些手机！"}, {"url": "https://b23.tv/BV1SE421w7Hq", "title": "【火影动画】你 的 鸣 子 ！"}, {"url": "https://b23.tv/BV1xi421a7QA", "title": "驴唇不对马嘴"}, {"url": "https://b23.tv/BV1vx4y147wU", "title": "作者食物中毒做出来的游戏"}, {"url": "https://b23.tv/BV196YheQEJm", "title": "今天做炸土豆条给爸爸吃"}, {"url": "https://b23.tv/BV16U411U71e", "title": "三十年河东三十年河西"}, {"url": "https://b23.tv/BV1kr421M7Ki", "title": "当我们在MC里开了家「空岛汉堡店」!？"}, {"url": "https://b23.tv/BV1eU411U7VY", "title": "太痛了！感动百万人，短短几分钟却是无数人的缩影！"}, {"url": "https://b23.tv/BV1ZT42167Ao", "title": "我把中国队夺冠瞬间做成了动画！！！"}, {"url": "https://b23.tv/BV1bx4y147b6", "title": "探秘美国总统一日三餐！特朗普吃什么？没人比他更懂美食！"}, {"url": "https://b23.tv/BV1eS42197kL", "title": "MC洪灾启示录:当我的世界一直下雨......"}, {"url": "https://b23.tv/BV1Ew4m1k7v4", "title": "上映前就被骂的徐峥新电影，我看完后，却骂不出来【7000字长文解析】"}, {"url": "https://b23.tv/BV1Ji421a7ex", "title": "【人生态度】声优翻唱—刘十四"}, {"url": "https://b23.tv/BV1U4421Z793", "title": "我重生了！回到了2018年，我这次一定要..."}, {"url": "https://b23.tv/BV1Vx4y147tH", "title": "当我用手机偷看躲在门后的小猫…（小猫你好冒昧！"}, {"url": "https://b23.tv/BV1TT421r7Ue", "title": "胡子哥：不能让老外只知道日本抹茶和焙茶"}, {"url": "https://b23.tv/BV1tH4y1c7Q6", "title": "我们为什么讨厌饭圈文化"}, {"url": "https://b23.tv/BV1HE4m1d7K9", "title": "不让我去巴黎，我就在宿舍办奥运！"}, {"url": "https://b23.tv/BV1ox4y1x7BM", "title": "选错就死！"}, {"url": "https://b23.tv/BV1KW42197ua", "title": "研究生午休时间，用工作电脑看视频，被重罚，自愿双倍完成毕业要求。"}, {"url": "https://b23.tv/BV1cb421J7Tt", "title": "小时候的顶级理解"}, {"url": "https://b23.tv/BV1sE4m1R7hf", "title": "我清正廉洁了一辈子，终于用上皮肤了"}, {"url": "https://b23.tv/BV1c1421t7ZB", "title": "听说你们想看我俩联动？哈哈哈…"}, {"url": "https://b23.tv/BV1H4421S7x9", "title": "40名UP主在MC中模拟海盗！谁能活到最后？「我的世界海盗模拟」"}, {"url": "https://b23.tv/BV1eZ421N7Tx", "title": "B 站 等 级 压 制 现 状"}, {"url": "https://b23.tv/BV1XW42197eG", "title": "棒棒糖，你太依赖猪猪侠了"}, {"url": "https://b23.tv/BV1Jf421B7b9", "title": "老板真好，让我不用来上班了"}, {"url": "https://b23.tv/BV1ur421M7b3", "title": "【鸣潮cos群像】漂泊者，这个温泉…一点也不烫"}, {"url": "https://b23.tv/BV1gy411q7qt", "title": "90后的童年游戏"}, {"url": "https://b23.tv/BV14HaQeaErh", "title": "B站军迷最爱的“真理的声音”来喽！"}, {"url": "https://b23.tv/BV1sE421w7Hw", "title": "《N命速通》八番出口！亿！镜！到！底！"}, {"url": "https://b23.tv/BV1Hi421a7yH", "title": "【黑神话：悟空】《往生咒》在国外鲨疯了！赛博诵经让老外陷入疯狂！"}, {"url": "https://b23.tv/BV1NS421972h", "title": "【手书】小猫咪屁股翘翘哦【明日方舟】"}, {"url": "https://b23.tv/BV1qS411w7NY", "title": "【时代少年团】「叁重楼」L3-《梦》舞蹈版"}, {"url": "https://b23.tv/BV1Vx4y1s7UJ", "title": "【原创编舞】佩佩舞！✨一起跳！✨全曲宅舞 - Mystic Light Quest【明日方舟】"}, {"url": "https://b23.tv/BV1eS411w78S", "title": "我做了一个可以吃的杠铃！"}, {"url": "https://b23.tv/BV1XS421X7yB", "title": "《打折》"}, {"url": "https://b23.tv/BV1Xf421q7pX", "title": "学做80年代的鱼香肉丝！最有饭张力的一期"}, {"url": "https://b23.tv/BV1wf421i7pi", "title": "小伙在北京的出租屋出问题了有点扛不住，煮一锅挂面压压惊"}, {"url": "https://b23.tv/BV1mE4m1R7TG", "title": "清晨5点钟的蓝调时刻."}, {"url": "https://b23.tv/BV1ki421h7qm", "title": "也许我们每个人都在参加自己行业中的“奥运”吧？"}, {"url": "https://b23.tv/BV1bz421i7sW", "title": "幻术惊魂，悬案重审，差点引出惊天巨变？奇幻悬疑剧《唐朝诡事录》第八案【参天楼】"}, {"url": "https://b23.tv/BV1g4421S7is", "title": "胖龙魔怔了，啃着大牛蹄，还在手舞足蹈，这谁看了不心疼"}, {"url": "https://b23.tv/BV1hw4m1k7En", "title": "16万人评分9.1的专辑!20年后的七里香还有秘密?丨HOPICO"}, {"url": "https://b23.tv/BV1wM4m11716", "title": "不是哥们？"}, {"url": "https://b23.tv/BV1JU411S7Za", "title": "刚安顿完新来的三十多只小猫们就下起了大雨"}, {"url": "https://b23.tv/BV1rb421J7NJ", "title": "我一百万啦！"}, {"url": "https://b23.tv/BV1Ki421a76G", "title": "我的世界：钻石装备批发机，试炼大厅：哥们，你来进货的？"}, {"url": "https://b23.tv/BV18Z421N7k2", "title": "雏田：“因为我，最喜欢鸣人了”"}, {"url": "https://b23.tv/BV1Yi421a75C", "title": "随机事件空岛生存？系好安全带，车速有点快！"}, {"url": "https://b23.tv/BV13E421A7Lj", "title": "【穿越火线16周年纯享版】秦朝老兵专用BGM！"}, {"url": "https://b23.tv/BV1FZ421M7VY", "title": "6款不动脑便利店调饮， 有手谁都会"}, {"url": "https://b23.tv/BV1gE421A7TL", "title": "一镜到底!! 国人速通丧心病狂【螺旋跑酷塔】一命速通!"}, {"url": "https://b23.tv/BV19T421k7gm", "title": "跟朋友出远门只有你会开车时："}, {"url": "https://b23.tv/BV1tn4y1f7rF", "title": "不好意思帅到你了"}, {"url": "https://b23.tv/BV114421Z7U9", "title": "过 分 了 吧"}, {"url": "https://b23.tv/BV12y411e74T", "title": "120秒，白嫖公司上百万？100人“零元购”体验！"}, {"url": "https://b23.tv/BV1Y4421Z7fi", "title": "这么实诚的自助，现在真的是不多见了！"}, {"url": "https://b23.tv/BV1Aw4m1k7EQ", "title": "被电影带火的美食：大力水手原来没骗人，吃菠菜还真能长肌肉啊！"}, {"url": "https://b23.tv/BV1SE421w7B3", "title": "越过5291个人的车窗，看他们途中的故事"}, {"url": "https://b23.tv/BV1JZ421N7vp", "title": "浴室里挂三折镜的理由找到了，太适合独自“发疯”了，可以玩一天！"}, {"url": "https://b23.tv/BV1LZ421K7Dv", "title": "离谱！当我突然跟女友坦白分手理由…又把她惹哭了！"}, {"url": "https://b23.tv/BV1XE4m1X7rL", "title": "终于带芬兰表妹一家回成都！第一次来四川看啥都新奇！被团圆宴惊艳直呼太感动！逛夜市玩水上世界家乡美景赞叹不已！震惊众人！"}, {"url": "https://b23.tv/BV16w4m1k7Lr", "title": "【轰】怀胎三年就生了这颗蛋？！"}, {"url": "https://b23.tv/BV1VW42197S8", "title": "《纸嫁衣7卿不负》主题曲《痴情客》"}, {"url": "https://b23.tv/BV1Df421q7eo", "title": "哈哈哈哈哈关键词游戏"}, {"url": "https://b23.tv/BV1Yr421K7d2", "title": "《狂热复苏》合集！~"}, {"url": "https://b23.tv/BV1tw4m1k7jz", "title": "超级真实硬核生存「群峦重生」#6"}, {"url": "https://b23.tv/BV1Fi421a7bw", "title": "如果来生还可能继续，再用尽一生找寻，你在哪里"}, {"url": "https://b23.tv/BV19w4m1r7Xz", "title": "当我在Mc里拥有无限大的饱食度 且越吃越大 我的世界"}, {"url": "https://b23.tv/BV1W142187P1", "title": "1块钱的手机 我崩溃了"}, {"url": "https://b23.tv/BV1VE421w77G", "title": "【STN快报第七季67】如龙真人剧将让原作玩家高潮迭起"}, {"url": "https://b23.tv/BV1Pz421i78w", "title": "我服下画师途径魔药的一年"}, {"url": "https://b23.tv/BV1aM4m1y7tf", "title": "《朋克洛德核弹》"}, {"url": "https://b23.tv/BV1fW421X7gD", "title": "耗时一年！一口气看完被封前的查理九世全部讲了什么？！"}, {"url": "https://b23.tv/BV1vi421h7hh", "title": "《这是哪个器官想出来的》"}, {"url": "https://b23.tv/BV1Ui421h74J", "title": "大学生暑假现状"}, {"url": "https://b23.tv/BV18z421i77Q", "title": "黑手哥蜡像"}, {"url": "https://b23.tv/BV1KE4m1d7af", "title": "如果不是意外发现，他们将全部被当做垃圾倾倒，军人不是怕战死沙场，怕的是被后人所遗忘，英烈的尸骨已融入了泥土，但他们的功绩永不磨灭 \"致敬英雄；"}, {"url": "https://b23.tv/BV1tfYWe4EzC", "title": "这78883200秒我拍了94秒"}]