[{"url": "https://b23.tv/BV1paM1zqEiv", "title": "说的什么玩意？"}, {"url": "https://b23.tv/BV1HWMrz4Ebe", "title": "你好！测评一下领结婚证！"}, {"url": "https://b23.tv/BV1tgMzztEnA", "title": "《原神》丝柯克角色PV——「一个结束，一个开始」"}, {"url": "https://b23.tv/BV1C9M2z3ETU", "title": "《小鸟军校》全集·精华——【微电影】重映!"}, {"url": "https://b23.tv/BV1KwMyzuE8m", "title": "玩具梦核版《黑色幽默》"}, {"url": "https://b23.tv/BV1hGMCzkENq", "title": "“太多人被困在街角 ，迟迟不见绿灯信号”——《莫愁乡》"}, {"url": "https://b23.tv/BV155MSziEtM", "title": "“我的出租屋里真的有很多蟑螂，但我认识的粥批真的没有几个”"}, {"url": "https://b23.tv/BV11SMUzQEav", "title": "特厨探店 |出现了!建号以来以来第一个全好评餐厅！—芙蓉凰"}, {"url": "https://b23.tv/BV13DMCz2EaU", "title": "无敌食尸诡大合集！"}, {"url": "https://b23.tv/BV1TQMTzgED2", "title": "比奇堡旷世奇才《莫愁乡》——“我被困在了蟹堡王里”"}, {"url": "https://b23.tv/BV1WWMuzTEFi", "title": "请看我的doro~"}, {"url": "https://b23.tv/BV1UMMzzfEBU", "title": "大合集：首富为了逼我跟他女儿碎觉，竟派人把我绑成粽子扔进车里"}, {"url": "https://b23.tv/BV1HNMMzhE5z", "title": "【小市民/蔷薇宴/MAD】分手推理式·"}, {"url": "https://b23.tv/BV1sxM1zrEea", "title": "“只因家教，冰淇淋我从来不用嘴吃”"}, {"url": "https://b23.tv/BV1VtMgzWEhM", "title": "冰岛很贵，但是很美！"}, {"url": "https://b23.tv/BV1fKMBz3E8j", "title": "1秒能拍44万帧？！高速摄影的代价是…"}, {"url": "https://b23.tv/BV1cTMMzFEZd", "title": "软萌女主，谁看了都想欺负一下【第一季完结】"}, {"url": "https://b23.tv/BV1G8MczcEaA", "title": "《风水の大师》"}, {"url": "https://b23.tv/BV12mM2zLExm", "title": "《大爱仙尊》 最强还原 全网首播"}, {"url": "https://b23.tv/BV176M3zPEZu", "title": "莫愁乡--（OfficialMusicVideo）亚细亚旷世奇才"}, {"url": "https://b23.tv/BV18MMuz7EBL", "title": "身体：给我…支棱起来！！！"}, {"url": "https://b23.tv/BV1BPMmzeEV5", "title": "女人请划走，你们看不懂"}, {"url": "https://b23.tv/BV13jMwzfEGL", "title": "“功夫教师  打进校园”"}, {"url": "https://b23.tv/BV1A7MDzpE99", "title": "【高燃】竟然真的有人可以复刻麦朵的六合大枪！"}, {"url": "https://b23.tv/BV1xHMCziEn4", "title": "(天命既定)1-8合集！我在噶前调戏了圣女 可她的表情怎么不太对劲？"}, {"url": "https://b23.tv/BV1nxMzz7ET2", "title": "孤独啊！世界上有太多孤独的人，害怕迈出第一步...——《绿皮书》"}, {"url": "https://b23.tv/BV1BxMtzmEzS", "title": "女厕每个洞都堵上 透明人进厕所都得留一套写真"}, {"url": "https://b23.tv/BV1y7MzzXExZ", "title": "为了彰显男女主爱情的伟大，绿茶男主竟要求柳如烟当众与你退婚！【P1-P9合集】"}, {"url": "https://b23.tv/BV1hSMCz7Eew", "title": "海水流归来处，沉于你的眼底——祁煜「当海湮没于海」PV公开！"}, {"url": "https://b23.tv/BV1cXTfzqEuH", "title": "《死 神 来 了》"}, {"url": "https://b23.tv/BV1mLMCz6ERX", "title": "那么现在…战斗开始"}, {"url": "https://b23.tv/BV1fKMBz3EsX", "title": "原来这就是18岁的她幻想的毕业旅行…"}, {"url": "https://b23.tv/BV1hAMzzAESm", "title": "不问永生【1-9合集】"}, {"url": "https://b23.tv/BV1zNMSzrERL", "title": "我竟然回到了高三时期！！！！"}, {"url": "https://b23.tv/BV1iQMBz6EZG", "title": "谁有我会烧？"}, {"url": "https://b23.tv/BV1ekM8zyELG", "title": "【速凌】疯医：跟我的黑海说去吧！"}, {"url": "https://b23.tv/BV1ShMkz6EJN", "title": "[全网第一]S前锋蒙眼手搓通关空中赛道"}, {"url": "https://b23.tv/BV1CKMHzTEEk", "title": "“我老了，但你的冒险才刚刚开始！”"}, {"url": "https://b23.tv/BV17hMTz9EgF", "title": "如果孩子与父母之间可以重新选择？"}, {"url": "https://b23.tv/BV112MyzMEN1", "title": "我们去外星球拍了几张照片"}, {"url": "https://b23.tv/BV1W7MzzXEz9", "title": "《打工皇帝养成记-厨师篇》"}, {"url": "https://b23.tv/BV1fGMgzYEyH", "title": "“这跟谈了有什么区别？！”"}, {"url": "https://b23.tv/BV16EMxzyESM", "title": "（超级还原）捷德奥特曼OP，但是我演的"}, {"url": "https://b23.tv/BV1jGTRzEEoG", "title": "原创动画手书《歌雀》｜致：在逆境中的你"}, {"url": "https://b23.tv/BV1V6MTzmE2d", "title": "别眨眼，视频每1秒都将狠狠冲击你们的认知"}, {"url": "https://b23.tv/BV1f5MgzwEYa", "title": "bro懂我的音乐"}, {"url": "https://b23.tv/BV1nEMAzjEBR", "title": "一帮人给我洗一辆电瓶车"}, {"url": "https://b23.tv/BV1GpMbzzEsm", "title": "筹备半年的中国美食餐车终于亮相芬兰市中心！开张第一天卖肉夹馍凉面引爆街头，各国老外瞳孔地震尖叫连连！"}, {"url": "https://b23.tv/BV1bKMNzAEBt", "title": "“女性角色与男性生物笑声”"}, {"url": "https://b23.tv/BV1rnMzzDEVQ", "title": "我被抄袭了"}, {"url": "https://b23.tv/BV156MuzxEDA", "title": "Re:佩恩从零开始的异世界生活！！！【二】"}, {"url": "https://b23.tv/BV18hMJzGESu", "title": "配完被朋友拿刀追了十几里地"}, {"url": "https://b23.tv/BV1z5MgzcEvw", "title": "班主任的孩子可真是个小聪明蛋！"}, {"url": "https://b23.tv/BV1KmM2zjEoZ", "title": "“谁懂小卡开口那一刻的救赎感”"}, {"url": "https://b23.tv/BV1rZM2zBEgd", "title": "你管这叫cos？"}, {"url": "https://b23.tv/BV178MzzyEgn", "title": "《如愿》德国钢琴家理解了歌词后，在上海街头的演绎。"}, {"url": "https://b23.tv/BV1kJMzzHEaL", "title": "新番时光机！十年前的观众都在看什么神片？「2015年4月篇」泛式"}, {"url": "https://b23.tv/BV1mYMkzuEoa", "title": "蛋仔派对：五分钟带你看完 蛋仔三周年所有重大更新爆料！超燃新英雄居然是咚咚羊？"}, {"url": "https://b23.tv/BV1zNMSzrEx5", "title": "《神秘歌曲》"}, {"url": "https://b23.tv/BV1Y7TrzqEP1", "title": "黄色是什么？？？"}, {"url": "https://b23.tv/BV1h5MmzoESM", "title": "一个重要的决定"}, {"url": "https://b23.tv/BV1wGM2zgEUv", "title": "空…空你寄哇？"}, {"url": "https://b23.tv/BV1zBMwzCEpk", "title": "不知不觉我已泪流满面，勇敢的小姑娘一定要好起来吧，会有很多人守护着你的！"}, {"url": "https://b23.tv/BV1MdMCzVEQx", "title": "LUCKY ME丨REMIX【狛枝凪斗手书】"}, {"url": "https://b23.tv/BV1zoMyzhEwc", "title": "花10元去趟宿舍南极是什么体验"}, {"url": "https://b23.tv/BV1NqMbzFESn", "title": "学了这个再找不到家长藏的手机，你就是这个👍"}, {"url": "https://b23.tv/BV1UZMpznEKq", "title": "400万云设计师 继续迭代求生吊坠"}, {"url": "https://b23.tv/BV1NmM2zjEXs", "title": "没有灵根真的没法修仙吗？！！"}, {"url": "https://b23.tv/BV1mBMgz1EZc", "title": "父爱是沉默的守护，笨拙却深沉"}, {"url": "https://b23.tv/BV1xVMzzxESd", "title": "ps乐高像素效果竟然如此简单！"}, {"url": "https://b23.tv/BV1kmMkzfEMA", "title": "【火柴人VS学习】数学物理几何编程全面解析大合集"}, {"url": "https://b23.tv/BV14gMzztEZS", "title": "声纹锁定缅北诈骗犯，落地直接被捕"}, {"url": "https://b23.tv/BV1k2Mkz8ESV", "title": "他们说澳门1天就够…但我吃了3天3夜！！"}, {"url": "https://b23.tv/BV1hXMCzLEkD", "title": "一个00后平行穿越到另一个世界当老师，自己淋过雨，得往学生头上浇开水，开始了他的老六行为！！！"}, {"url": "https://b23.tv/BV1qXM7zJEVT", "title": "中国BOY终于请客了！"}, {"url": "https://b23.tv/BV1uqMyzLE6u", "title": "你高考后 还有最后亿场考试~"}, {"url": "https://b23.tv/BV1YuM1zpELw", "title": "鸣潮最新活动，荣耀之丘无敌卡组，保姆级教学！刀刀十万！随便过布兰特。"}, {"url": "https://b23.tv/BV1pLMAzEEME", "title": "人体气球挑战 🎈"}, {"url": "https://b23.tv/BV1jeMDzrEhF", "title": "无尽爷爷蹲坑版1~3合集"}, {"url": "https://b23.tv/BV1CtMCzaEMo", "title": "祭侄文稿最悲惨段落海外展出竟被用作食品包装！看懂书法艺术有多重要？"}, {"url": "https://b23.tv/BV1HoMxzUE64", "title": "湖北妈妈岗引爆热搜、被全网讨伐，妈妈岗到底做错了什么？"}, {"url": "https://b23.tv/BV1DtMMzyEoN", "title": "【官方MV】MAO！- 洛天依&神山羊-有機酸"}, {"url": "https://b23.tv/BV1b2MtzPEQk", "title": "番茄巅峰榜是神作？番茄难道真的没有神作/仙草吗？"}, {"url": "https://b23.tv/BV1rPMMzwEfY", "title": "蛋仔派对：听声猜AI山海经！共二十个角色，满分100。你能拿多少？"}, {"url": "https://b23.tv/BV1WhM1zuECk", "title": "蛋仔派对：能领蛋币的地图重出江湖？不是蛋仔你来真的呀！"}, {"url": "https://b23.tv/BV1gMMuzjEVY", "title": "表面上你是城市之光，暗地里却是暗黑狂魔"}, {"url": "https://b23.tv/BV126MyzGEB3", "title": "伊朗遭以色列袭击损失惨重，升旗小能手这次将如何应对？"}, {"url": "https://b23.tv/BV1kCM6z9E4r", "title": "花 火 衣 橱 大 公 开"}, {"url": "https://b23.tv/BV1KwMgz3ELX", "title": "应粉丝要求挑战30块钱吃一天！居然还能管饱？"}, {"url": "https://b23.tv/BV1x4MmzUEGU", "title": "《使命召唤》联动《我的世界》凋零风暴！组合包特殊检视【自制动画】"}, {"url": "https://b23.tv/BV1R8MGzfE55", "title": "“我要回家了，十八岁的我自己…”"}, {"url": "https://b23.tv/BV1NsTqz7EUH", "title": "这个小姐姐家的狗好凶，幸好我会狗语"}, {"url": "https://b23.tv/BV1ogM6zjEZR", "title": "【镜水】生死不明！王镜水原神已经被炼化！"}, {"url": "https://b23.tv/BV1RsMyzpEMr", "title": "1小时循环《句句属实》我说的都是实话呀！"}, {"url": "https://b23.tv/BV1sTMAzREDX", "title": "被资本做猫了！😨【崩铁动画】"}, {"url": "https://b23.tv/BV1rKMJzbE7u", "title": "赶紧写作业去吧！整这些东西做什么啊！"}, {"url": "https://b23.tv/BV1K6MyzVEXA", "title": "伺机而动"}, {"url": "https://b23.tv/BV1VUM1zdEPr", "title": "伊以“大战”一触即发：最大的热点依然不在伊以"}, {"url": "https://b23.tv/BV1PaM4zRErJ", "title": "洛杉矶暴乱不可怕，有中国大妈守护世界和平!"}, {"url": "https://b23.tv/BV1GyMuzXEp7", "title": "第一集| 猩红公寓，我能看到隐藏信息！"}, {"url": "https://b23.tv/BV13mMuzDEcu", "title": "人为刀俎"}, {"url": "https://b23.tv/BV1G4TfzsE3T", "title": "[原版补档] 第2.5套广播体操——现在开始！"}]