[{"url": "https://www.kuaishou.com/short-video/3x9ckpui5uwaf4i", "title": "画好强国建设民族复兴最大同心圆"}, {"url": "https://www.kuaishou.com/short-video/3xh3atcnqthnfmi", "title": "中国女排对战土耳其"}, {"url": "https://www.kuaishou.com/short-video/3xhsn5gtvfc2b66", "title": "朱婷扮鬼脸"}, {"url": "https://www.kuaishou.com/short-video/3xdr5iwnbbvnfru", "title": "中国制造永远不会让你失望"}, {"url": "https://www.kuaishou.com/short-video/3x2dn2yba5d5vpq", "title": "国乒男团对战印度"}, {"url": "https://www.kuaishou.com/short-video/3x8g7hc6v33ghxg", "title": "潘展乐无缘闭幕式旗手"}, {"url": "https://www.kuaishou.com/short-video/3x8gwyi5vpfj49e", "title": "马龙王楚钦3比0印度组合"}, {"url": "https://www.kuaishou.com/short-video/3xpydr33v59w4fm", "title": "樊振东一单"}, {"url": "https://www.kuaishou.com/short-video/3xqwafnvvz3w64m", "title": "日本核污染水本周开始第8轮排海"}, {"url": "https://www.kuaishou.com/short-video/3xw68c8kmviuetk", "title": "光头强：我的头发是真发"}, {"url": "https://www.kuaishou.com/short-video/3x6wnwpzfeq8kgg", "title": "戴向宇方声明"}, {"url": "https://www.kuaishou.com/short-video/3x2snkbdsf8an8w", "title": "张昊唯回应曝戴向宇嫖娼"}, {"url": "https://www.kuaishou.com/short-video/3xeyqqmsw6gspdi", "title": "运动并非只有早上才好"}, {"url": "https://www.kuaishou.com/short-video/3x3ztfxzec227de", "title": "中国女排加油"}, {"url": "https://www.kuaishou.com/short-video/3x7vycucdpr2kvy", "title": "奥运今日赛事看点"}, {"url": "https://www.kuaishou.com/short-video/3x63eysj57e8cqa", "title": "以军打死黎巴嫩真主党一指挥官"}, {"url": "https://www.kuaishou.com/short-video/3xdkxkhq9gk6sww", "title": "邓紫棋邀请郑钦文看她演唱会"}, {"url": "https://www.kuaishou.com/short-video/3xwjzbyknqbjrpq", "title": "李政道将与妻子合葬于苏州"}, {"url": "https://www.kuaishou.com/short-video/3xv7wsu3y46rqn4", "title": "日本樱岛火山喷发烟柱高达3000米"}, {"url": "https://www.kuaishou.com/short-video/3xk4n3fchw4d36a", "title": "潘展乐拿两只小象亲亲"}, {"url": "https://www.kuaishou.com/short-video/3xrd27xsxdhkuiw", "title": "中国女排赢下首局"}, {"url": "https://www.kuaishou.com/short-video/3xwc2i5453xpvfs", "title": "这一路走到奥运真的不容易"}, {"url": "https://www.kuaishou.com/short-video/3xi7cvc6xfs7b3a", "title": "全红婵陈芋汐决赛冲金"}, {"url": "https://www.kuaishou.com/short-video/3x84jp2vn8xi8ks", "title": "看巴黎早上好就像在看脱口秀"}, {"url": "https://www.kuaishou.com/short-video/3xrvwak8fexba2a", "title": "国乒男团巴黎首秀"}, {"url": "https://www.kuaishou.com/short-video/3xc3m796jix3dn2", "title": "王楚钦交替使用两副球拍训练"}, {"url": "https://www.kuaishou.com/short-video/3x223wrmhrqscf9", "title": "陕西省政协原主席韩勇被提起公诉"}, {"url": "https://www.kuaishou.com/short-video/3x47mwkakwysrna", "title": "我俩在一起不是早晚的事吗"}, {"url": "https://www.kuaishou.com/short-video/3xgn3rjmtveaiwk", "title": "中国女排冲击四强"}, {"url": "https://www.kuaishou.com/short-video/3xkr9adnm2ibv9m", "title": "和平精英上线新皮肤卖崽青蛙"}, {"url": "https://www.kuaishou.com/short-video/3x9iwjcnri539ye", "title": "crush已为我着迷"}, {"url": "https://www.kuaishou.com/short-video/3xq294py7kvkw2m", "title": "你最讨厌什么样的人街头采访"}, {"url": "https://www.kuaishou.com/short-video/3xzasdikjkgr7wg", "title": "邹敬园回应体操队内争议"}, {"url": "https://www.kuaishou.com/short-video/3xurpahyyfyhx2w", "title": "冯小刚怒推路人 当事人发声"}, {"url": "https://www.kuaishou.com/short-video/3xq83nva572f48i", "title": "以色列向加沙移交80多具遗体"}, {"url": "https://www.kuaishou.com/short-video/3xb4ymezvh2qdvs", "title": "精潮小妹的经典事件"}, {"url": "https://www.kuaishou.com/short-video/3x63beree44y63u", "title": "潘展乐说汪顺身材世界第一"}, {"url": "https://www.kuaishou.com/short-video/3xashqq79mg6sk2", "title": "体育总局回应干部发表不当言论"}, {"url": "https://www.kuaishou.com/short-video/3xbkfht6b8p7z34", "title": "刺客伍六七与茶啊二中的梦幻联动"}, {"url": "https://www.kuaishou.com/short-video/3xvxbyet6ypz9as", "title": "再见赏金 你好甜心"}, {"url": "https://www.kuaishou.com/short-video/3x52akfv923wsze", "title": "全球股市暴跌背后的原因"}, {"url": "https://www.kuaishou.com/short-video/3xghneqh849rvvy", "title": "冯彬女子铁饼摘银"}, {"url": "https://www.kuaishou.com/short-video/3xq9wzhthnjigtq", "title": "哈里斯获民主党总统候选人提名"}, {"url": "https://www.kuaishou.com/short-video/3xc2xzseby8vcak", "title": "全红婵陈芋汐10米台晋级决赛"}, {"url": "https://www.kuaishou.com/short-video/3x2uaweautsuq4k", "title": "潘展乐的巴黎奥运会战术"}, {"url": "https://www.kuaishou.com/short-video/3xpxhbs92nwchc2", "title": "来一场水灵灵的爆改"}, {"url": "https://www.kuaishou.com/short-video/3x5aj65nwas7fbe", "title": "英国骚乱蔓延至伯明翰"}, {"url": "https://www.kuaishou.com/short-video/3xrccdhujk5ha8q", "title": "潘展乐吐槽奥运村伙食太差"}, {"url": "https://www.kuaishou.com/short-video/3x3b5k67x54qahs", "title": "仿默杀片尾"}, {"url": "https://www.kuaishou.com/short-video/3xja98nehq67j76", "title": "中国花游团体技术自选第一"}, {"url": "https://www.kuaishou.com/short-video/3xrx96whnp2b56k", "title": "全红婵半拉着裤腿就跑"}, {"url": "https://www.kuaishou.com/short-video/3xx673knksn84yu", "title": "傅园慧说潘展乐是游泳之神下凡"}, {"url": "https://www.kuaishou.com/short-video/3x79cbb63z4ezh2", "title": "国产大飞机C919开始执飞京陕快线"}, {"url": "https://www.kuaishou.com/short-video/3xn6c3s7qvszim2", "title": "国乒女团开门红"}, {"url": "https://www.kuaishou.com/short-video/3x5c6sb6thzq6t2", "title": "孙颖莎世排第一9000分"}, {"url": "https://www.kuaishou.com/short-video/3xbgwm97jpyhppk", "title": "谁将担任闭幕式旗手"}, {"url": "https://www.kuaishou.com/short-video/3xu8g2r58dizspu", "title": "男子监视期间杀害堂妹今日开庭"}, {"url": "https://www.kuaishou.com/short-video/3xwz2hzc9fari9q", "title": "张博恒发快手总结奥运之旅"}, {"url": "https://www.kuaishou.com/short-video/3xh2v6zedi4wwn2", "title": "专家：伊朗对以报复行动迫在眉睫"}, {"url": "https://www.kuaishou.com/short-video/3x3qhfccdaa5fse", "title": "中国队第21金"}, {"url": "https://www.kuaishou.com/short-video/3xmnjpsrqbehr6q", "title": "湖南航空回应空姐上班穿平底鞋"}, {"url": "https://www.kuaishou.com/short-video/3xv54imd7crwk3q", "title": "老一辈人修理东西的方式"}, {"url": "https://www.kuaishou.com/short-video/3xx2xhbz2vxmx86", "title": "日经指数今日开盘大涨"}, {"url": "https://www.kuaishou.com/short-video/3xcrrkz2qvxgfe2", "title": "摇太阳舞蹈挑战"}, {"url": "https://www.kuaishou.com/short-video/3xjnefjd2y3kif6", "title": "楚新钓南罡北冥感人师徒情"}, {"url": "https://www.kuaishou.com/short-video/3xxgj9j2ezqyyyu", "title": "7月辟谣榜"}, {"url": "https://www.kuaishou.com/short-video/3xf9f2psdj5i3zc", "title": "菲警方解救2名遭绑架的中国女子"}, {"url": "https://www.kuaishou.com/short-video/3x4d37rug9x2cmg", "title": "王者联动狐妖小红娘"}, {"url": "https://www.kuaishou.com/short-video/3x8tsfwj4b8mq52", "title": "摇太阳舞蹈挑战"}, {"url": "https://www.kuaishou.com/short-video/3xjdeixtd6kuns2", "title": "美国队所有人都找潘展乐握手"}, {"url": "https://www.kuaishou.com/short-video/3xg99qmjhpy458a", "title": "全国新增15条河流发生超警洪水"}, {"url": "https://www.kuaishou.com/short-video/3x66zmh7jr3898w", "title": "李政道逝世"}, {"url": "https://www.kuaishou.com/short-video/3xi836bmydfi9kq", "title": "四川康定泥石流已致10死17失联"}, {"url": "https://www.kuaishou.com/short-video/3xf9drivsytgcbg", "title": "楚新钓新副本妖山水库开启"}, {"url": "https://www.kuaishou.com/short-video/3x4yi7bw56xfcrq", "title": "潘展乐的奖牌蚊帐是爷爷设计的"}, {"url": "https://www.kuaishou.com/short-video/3x5y9nizriy47b2", "title": "关晓彤说潘展乐是飞人"}, {"url": "https://www.kuaishou.com/short-video/3x2dka9nin67qhm", "title": "七夕脱单小技巧"}, {"url": "https://www.kuaishou.com/short-video/3x9ykaqn96ntqp4", "title": "专家谈董军防长发出统一最强音"}, {"url": "https://www.kuaishou.com/short-video/3xi4veiidnbcawi", "title": "乌克兰选手赛场睡觉醒来夺冠"}, {"url": "https://www.kuaishou.com/short-video/3x8zgmavr2ijq3q", "title": "人民币对美元汇率一度升破7.12"}, {"url": "https://www.kuaishou.com/short-video/3xsphcghcdbb9j6", "title": "中国游泳队花名大赏"}, {"url": "https://www.kuaishou.com/short-video/3x7ej99jtbhkv64", "title": "破洞裤秒变短裤"}, {"url": "https://www.kuaishou.com/short-video/3x87s9imbw4rn64", "title": "假如你闺蜜是奥运冠军"}, {"url": "https://www.kuaishou.com/short-video/3xdakm6b9pvb3hy", "title": "倪夏莲谈乒乓球饭圈文化"}, {"url": "https://www.kuaishou.com/short-video/3xix7i2ziv56yfw", "title": "苏炜德回应掉杠等失误"}, {"url": "https://www.kuaishou.com/short-video/3x22qfqy2n7mjny", "title": "美国一奥运选手兴奋剂阳性"}, {"url": "https://www.kuaishou.com/short-video/3xv43tuhhgtnru9", "title": "我也想当个被宠的小孩"}, {"url": "https://www.kuaishou.com/short-video/3xcjntevqabt2wm", "title": "怎么八点四十五了"}, {"url": "https://www.kuaishou.com/short-video/3xgdwd2bzxf685q", "title": "同一片天 为什么好久不见"}, {"url": "https://www.kuaishou.com/short-video/3xts7wyecbkci6e", "title": "用中国色打开锦绣山河"}, {"url": "https://www.kuaishou.com/short-video/3xtdntc4d2d892y", "title": "马英九：两岸开战死伤都是中国人"}, {"url": "https://www.kuaishou.com/short-video/3xet2wrfztyqzbw", "title": "梦泪孩子取名大赛"}, {"url": "https://www.kuaishou.com/short-video/3x86cqwdn63jw2c", "title": "中美生活圈差异"}, {"url": "https://www.kuaishou.com/short-video/3x76sw59bw9sap6", "title": "全红婵比赛前一天在拆乌龟盲盒"}, {"url": "https://www.kuaishou.com/short-video/3x4vqnmtn6si3za", "title": "潘展乐 外耗所有人"}, {"url": "https://www.kuaishou.com/short-video/3x7yaam9hv74rki", "title": "可以预约你一起过七夕节吗"}, {"url": "https://www.kuaishou.com/short-video/3xry7awt7vrr2hu", "title": "潘展乐说自己天生反骨"}, {"url": "https://www.kuaishou.com/short-video/3xyvutertfmgkq9", "title": "日韩股市为何反弹"}, {"url": "https://www.kuaishou.com/short-video/3xnjqti2crvu9fu", "title": "潘展乐：2金1银挺满意的"}, {"url": "https://www.kuaishou.com/short-video/3xa6ur9zzz7izx6", "title": "起猛了看到狗子骑电动车了"}, {"url": "https://www.kuaishou.com/short-video/3xp8x569gaa3kxi", "title": "潘展乐说会继续打破美国队垄断"}, {"url": "https://www.kuaishou.com/short-video/3xmig292spj6tjm", "title": "世界上没有真正的感同身受"}, {"url": "https://www.kuaishou.com/short-video/3xzy9zxwcjhsxay", "title": "邹敬园夺男子双杠金牌"}, {"url": "https://www.kuaishou.com/short-video/3x3wtpkc85yz69m", "title": "恭喜小胖预言成功"}, {"url": "https://www.kuaishou.com/short-video/3xz6si8m3ceuifg", "title": "我们的爱总有时差"}, {"url": "https://www.kuaishou.com/short-video/3xdunwie9ex6xxk", "title": "互换午餐挑战"}, {"url": "https://www.kuaishou.com/short-video/3xnxahncrtih5em", "title": "谢震业放弃200米单项"}, {"url": "https://www.kuaishou.com/short-video/3xc22rek246upqg", "title": "我爱看的带货视频"}, {"url": "https://www.kuaishou.com/short-video/3xxi3buz3nbi2z4", "title": "有个吃货女友是什么体验"}, {"url": "https://www.kuaishou.com/short-video/3xcgnw4jk5f52s9", "title": "潘展乐瞥了眼美国队说这怎么说啊"}, {"url": "https://www.kuaishou.com/short-video/3x4kqe24wd64x9e", "title": "专家评以色列屡屡上门搞暗杀"}, {"url": "https://www.kuaishou.com/short-video/3xhjbi5pykjnspi", "title": "郑钦文无缘闭幕式旗手"}, {"url": "https://www.kuaishou.com/short-video/3x3whg5573gg3yq", "title": "张雨霏晒1银5铜告别巴黎奥运会"}, {"url": "https://www.kuaishou.com/short-video/3xphv74w95up3j4", "title": "一名中国导游意大利遭遇车祸身亡"}, {"url": "https://www.kuaishou.com/short-video/3x56myzw6henz26", "title": "王者联动狐妖小红娘"}, {"url": "https://www.kuaishou.com/short-video/3xtna6izerqen6k", "title": "那些年拍过的尴尬视频"}, {"url": "https://www.kuaishou.com/short-video/3x2uhrmubnppq62", "title": "nasty舞蹈挑战"}, {"url": "https://www.kuaishou.com/short-video/3xk88pzp6ecf5dq", "title": "人民币狂拉黄金白银大跌"}, {"url": "https://www.kuaishou.com/short-video/3xq6f5wsfzx7wgk", "title": "这次是真当上陪嫁丫鬟了"}, {"url": "https://www.kuaishou.com/short-video/3xjwxn6vezxruxy", "title": "以部长称让200万加沙人饿死合理"}, {"url": "https://www.kuaishou.com/short-video/3xjx2e7qt2vxp9e", "title": "孙颖莎称团体第一场发挥正常"}, {"url": "https://www.kuaishou.com/short-video/3xe8up39gtwg969", "title": "潘展乐自豪喊话外国人"}, {"url": "https://www.kuaishou.com/short-video/3xmuvxv7ptmd464", "title": "nasty舞蹈挑战"}, {"url": "https://www.kuaishou.com/short-video/3x2ktcmqfpqsp74", "title": "安洗莹炮轰韩国羽协"}, {"url": "https://www.kuaishou.com/short-video/3xu5w4d5vj8pj4q", "title": "日韩股市大幅反弹"}, {"url": "https://www.kuaishou.com/short-video/3xsfs44cp7bsmgm", "title": "为二次元热爱应援"}, {"url": "https://www.kuaishou.com/short-video/3xbexm98yz79j9s", "title": "潘展乐说这段采访先别播"}, {"url": "https://www.kuaishou.com/short-video/3xa36jie22z2fsg", "title": "樊振东回应法国国家足球队的祝贺"}, {"url": "https://www.kuaishou.com/short-video/3xfkwnfdk8fmyds", "title": "我们的爱总有时差"}, {"url": "https://www.kuaishou.com/short-video/3xb94ciwxx99nnk", "title": "nasty舞蹈挑战"}, {"url": "https://www.kuaishou.com/short-video/3x5vr78uec3b46m", "title": "国产HPV疫苗降价至一杯奶茶钱"}, {"url": "https://www.kuaishou.com/short-video/3x7f3f6macmk3pe", "title": "李政道传奇人生"}, {"url": "https://www.kuaishou.com/short-video/3xbzjwtuyn3vwv4", "title": "全红婵赛前训练表演炸鱼"}, {"url": "https://www.kuaishou.com/short-video/3xhmbhqazkae47q", "title": "郑中基宣布退圈"}, {"url": "https://www.kuaishou.com/short-video/3xf2t8xjwzx4x6w", "title": "四川康定泥石流致9遇难18失联"}, {"url": "https://www.kuaishou.com/short-video/3xsemkskuxsdh79", "title": "中国代表团暂列金牌榜第一"}, {"url": "https://www.kuaishou.com/short-video/3x86y6wcre76p6m", "title": "中国射击队10枚奖牌收官"}, {"url": "https://www.kuaishou.com/short-video/3xvsdxtwc4m4zh6", "title": "马英九：两岸问题理应两岸自己谈"}, {"url": "https://www.kuaishou.com/short-video/3xb68utcvsx225i", "title": "岳云鹏要请凡尘组合听相声"}, {"url": "https://www.kuaishou.com/short-video/3x2jtp4acdd3mx4", "title": "马斯克：英国内战不可避免"}, {"url": "https://www.kuaishou.com/short-video/3xawjfn9yw5emva", "title": "自尊常常将人拖着 把爱都走曲折"}, {"url": "https://www.kuaishou.com/short-video/3x4nqa7w24h2ex2", "title": "以军发现巨型隧道"}, {"url": "https://www.kuaishou.com/short-video/3xycefwwwwz5xpy", "title": "潘展乐端水大师"}, {"url": "https://www.kuaishou.com/short-video/3xnvri45h6ftpqw", "title": "李越宏五枪全中"}, {"url": "https://www.kuaishou.com/short-video/3xjztckt58a3f2m", "title": "张雨霏就没下过领奖台"}, {"url": "https://www.kuaishou.com/short-video/3xvbnjch3cv895q", "title": "潘展乐“吹的牛”都实现了"}, {"url": "https://www.kuaishou.com/short-video/3xfaymwk9qysyvq", "title": "三人相拥那一刻体育无国界"}, {"url": "https://www.kuaishou.com/short-video/3x5idtauz4jyd54", "title": "当游戏中不同位置经济第一时"}, {"url": "https://www.kuaishou.com/short-video/3xiqbwq9nxyxchy", "title": "假如各科老师被锁房间里"}, {"url": "https://www.kuaishou.com/short-video/3xnbp4kyvbhyryk", "title": "英国赫尔多家商店遭暴徒洗劫"}, {"url": "https://www.kuaishou.com/short-video/3xnha7kg4avvudw", "title": "当班里新来了个拽姐"}, {"url": "https://www.kuaishou.com/short-video/3xmaag6ge73p7ia", "title": "见郑历史钦尽全力举世文名"}, {"url": "https://www.kuaishou.com/short-video/3xmgjb5rww5pfjg", "title": "当我在高铁上奇葩化妆"}, {"url": "https://www.kuaishou.com/short-video/3xvgr2casdvhccu", "title": "悬溺舞蹈挑战"}, {"url": "https://www.kuaishou.com/short-video/3x2t2c8449d55s9", "title": "入戏一夏你有没有这么尴尬过"}, {"url": "https://www.kuaishou.com/short-video/3xuqu73i5a59zme", "title": "新生群的聊天动静"}, {"url": "https://www.kuaishou.com/short-video/3xuji5cj8enc42q", "title": "美方称已增派军力助阵以色列"}, {"url": "https://www.kuaishou.com/short-video/3xa3h6ruq8wdsha", "title": "不认真一次反差挑战"}, {"url": "https://www.kuaishou.com/short-video/3x73taajkpq7yme", "title": "当你有个开明的家长"}, {"url": "https://www.kuaishou.com/short-video/3xqueajwjq6g476", "title": "趁女朋友睡着偷猫"}, {"url": "https://www.kuaishou.com/short-video/3xzeeigb8sfkvc2", "title": "李越宏25米手枪速射金牌"}, {"url": "https://www.kuaishou.com/short-video/3xwbvv9x73pmcyu", "title": "法国奥运会工作人员重拳出击"}, {"url": "https://www.kuaishou.com/short-video/3xk8i4zmdk8q84i", "title": "哈哈哈哈 一下子就不生气啦"}, {"url": "https://www.kuaishou.com/short-video/3xuhu3bcmu7qckm", "title": "孩子暑假不挨骂全靠反转"}, {"url": "https://www.kuaishou.com/short-video/3xtuebrq84d3fe2", "title": "骑手正在攻击你的外卖"}, {"url": "https://www.kuaishou.com/short-video/3x4cqpau7grgq5q", "title": "以色列被曝已准备好地下掩体"}, {"url": "https://www.kuaishou.com/short-video/3xjucvvdrrdnb92", "title": "为什么乌鸦像写字台"}, {"url": "https://www.kuaishou.com/short-video/3xtce7shmapupi4", "title": "朕要登基好魔性"}, {"url": "https://www.kuaishou.com/short-video/3x622kzvfpvgmn2", "title": "婚姻的意义是相互治愈"}, {"url": "https://www.kuaishou.com/short-video/3xe8zag5rx9gcri", "title": "鞠婧祎公主切氛围感美貌"}, {"url": "https://www.kuaishou.com/short-video/3xx8jyj6v9wmpxe", "title": "我能给你的 只有感觉"}, {"url": "https://www.kuaishou.com/short-video/3xidwtez7udizyg", "title": "孙佳俊说金牌有瑕疵"}, {"url": "https://www.kuaishou.com/short-video/3x8vbenk9xv7yt9", "title": "无法沟通的父母有多窒息"}, {"url": "https://www.kuaishou.com/short-video/3xzsw9jgf82ieas", "title": "保安是如何快速分辨出本校学生的"}, {"url": "https://www.kuaishou.com/short-video/3xen932uwzj54nk", "title": "当你进入喜羊羊的n+1世界"}, {"url": "https://www.kuaishou.com/short-video/3x9pawpxkqcn7pa", "title": "谁敢说咱英语老师不甜"}, {"url": "https://www.kuaishou.com/short-video/3xi3ssf9xe6ftgq", "title": "谷爱凌和潘展乐握手"}, {"url": "https://www.kuaishou.com/short-video/3xnjtyb4z2nagxw", "title": "北部湾实弹射击演练"}, {"url": "https://www.kuaishou.com/short-video/3xs4dkfneaprkmq", "title": "当我没睡醒时接面试官的电话"}, {"url": "https://www.kuaishou.com/short-video/3xkbiftszwtxf59", "title": "伊朗议长：将给以美历史性教训"}, {"url": "https://www.kuaishou.com/short-video/3xwrw6ei7fa24wy", "title": "冯彬母亲点赞女儿：我很满意"}, {"url": "https://www.kuaishou.com/short-video/3xkufvdygpkthhu", "title": "小炮子再次开启荒岛求生"}, {"url": "https://www.kuaishou.com/short-video/3x972mynp4wytwu", "title": "Faker确诊新冠"}, {"url": "https://www.kuaishou.com/short-video/3xzrdi54ugey4y4", "title": "菲船只在我仙宾礁附近海域聚集"}, {"url": "https://www.kuaishou.com/short-video/3xuf9rhbeqcq3vm", "title": "樊振东夺冠瞬间现场沸腾"}, {"url": "https://www.kuaishou.com/short-video/3xvckwc8wax46x2", "title": "孟令哲憾负智利选手无缘决赛"}, {"url": "https://www.kuaishou.com/short-video/3xtvc5id5xrsnfe", "title": "原神5.0版本卡池复刻角色分析"}, {"url": "https://www.kuaishou.com/short-video/3xa29gwtbn3uhsu", "title": "豆角是每个东北孩子的噩梦"}, {"url": "https://www.kuaishou.com/short-video/3x2kiig3u32y9au", "title": "张晓彬谈国内外足球青训区别"}, {"url": "https://www.kuaishou.com/short-video/3xrhzn5j874k8p2", "title": "杜普兰蒂斯打破世界纪录"}, {"url": "https://www.kuaishou.com/short-video/3x64d9x8csbzasc", "title": "你的crush降临了"}, {"url": "https://www.kuaishou.com/short-video/3xu6zfjpgyhvsyg", "title": "模仿潘展乐告状"}, {"url": "https://www.kuaishou.com/short-video/3xfi2fuwmnrk8i2", "title": "绍伊古访问伊朗"}, {"url": "https://www.kuaishou.com/short-video/3x2s8vudmpjm7xg", "title": "男朋友逃避家务的小聪明"}, {"url": "https://www.kuaishou.com/short-video/3xy8dfd45w43mw6", "title": "场地自行车女团争先赛中国第六"}, {"url": "https://www.kuaishou.com/short-video/3xpwnh9um4cgu46", "title": "孟加拉国总理辞职后前往印度"}, {"url": "https://www.kuaishou.com/short-video/3xsfmzakjakg2pa", "title": "孙颖莎状态"}, {"url": "https://www.kuaishou.com/short-video/3x4qn9pdqr3kkyw", "title": "张雨霏说每天三次尿检"}, {"url": "https://www.kuaishou.com/short-video/3x8uddc5x3x7bde", "title": "孙颖莎说对手的五环项链好看"}, {"url": "https://www.kuaishou.com/short-video/3x6ihtpq7hh9rbg", "title": "我答应你褪去身上的孩子气"}, {"url": "https://www.kuaishou.com/short-video/3x4bbjnayeer7i6", "title": "我的职业是网络主播"}, {"url": "https://www.kuaishou.com/short-video/3xn8mk9d7pp6b7g", "title": "卡点变妆挑战"}, {"url": "https://www.kuaishou.com/short-video/3xj98tk6myrdeii", "title": "李政道讣告"}, {"url": "https://www.kuaishou.com/short-video/3xb8eunccgcusz6", "title": "冯彬向女子铁饼金牌发起挑战"}, {"url": "https://www.kuaishou.com/short-video/3x3bgc3vq8j56gg", "title": "梧桐虽立 其心已空"}, {"url": "https://www.kuaishou.com/short-video/3x4t5zrey9y57ai", "title": "俄称不排除部署核导弹回应美"}, {"url": "https://www.kuaishou.com/short-video/3xp33pvg55jqqi2", "title": "金灿荣教授评伊朗宣战"}, {"url": "https://www.kuaishou.com/short-video/3xchjdts9cadj2u", "title": "以色列军机飞越黎巴嫩首都上空"}, {"url": "https://www.kuaishou.com/short-video/3xuzrzj7c8dxyu4", "title": "当你和朋友开始自驾游"}, {"url": "https://www.kuaishou.com/short-video/3xu5hm6pkfqeiic", "title": "我就这么水灵灵的变妆"}, {"url": "https://www.kuaishou.com/short-video/3xaze6mit8kdyhu", "title": "女子速度攀岩比赛攀岩表坏了"}, {"url": "https://www.kuaishou.com/short-video/3x6p3wim4s4nydc", "title": "不认真一次反差挑战"}, {"url": "https://www.kuaishou.com/short-video/3x9gn44dgama72c", "title": "新加坡一男生在学校遭多人霸凌"}, {"url": "https://www.kuaishou.com/short-video/3xc7yqat645b5fk", "title": "当你有个臭脸的姐姐"}, {"url": "https://www.kuaishou.com/short-video/3xqfmg6wk5r3awi", "title": "潘展乐凡尔赛实录"}, {"url": "https://www.kuaishou.com/short-video/3xdmik669dmj4ri", "title": "樊振东：巴黎更注重过程"}, {"url": "https://www.kuaishou.com/short-video/3xmgw7d5brgmp3g", "title": "伊拉克称已准备好为哈尼亚复仇"}, {"url": "https://www.kuaishou.com/short-video/3xnzs9jmi99n6tk", "title": "陈一冰说潘展乐未来可期"}, {"url": "https://www.kuaishou.com/short-video/3xgmxczfkkgs7hc", "title": "可以预约你一起过七夕节吗"}, {"url": "https://www.kuaishou.com/short-video/3xyzzwrz8rb5s6m", "title": "张雨霏赛后想吃螺蛳粉"}, {"url": "https://www.kuaishou.com/short-video/3xmxsssqv5smcji", "title": "曹利国奥运男子摔跤晋级8强"}, {"url": "https://www.kuaishou.com/short-video/3xnjc4sk6qf284k", "title": "中国打破美国队超过40年金牌垄断"}, {"url": "https://www.kuaishou.com/short-video/3xadfw8ppfkddki", "title": "新冠疑现抬头趋势"}, {"url": "https://www.kuaishou.com/short-video/3xgzs545az8zmf4", "title": "大人也开始玩登基游戏了"}, {"url": "https://www.kuaishou.com/short-video/3xckqht543kznti", "title": "千人千面 我永远爱我的那一面"}, {"url": "https://www.kuaishou.com/short-video/3xs9p85z236dvy2", "title": "黎真主党称向以北部发起袭击"}, {"url": "https://www.kuaishou.com/short-video/3xz8sx7nqdnvkwi", "title": "出月子的仪式感"}, {"url": "https://www.kuaishou.com/short-video/3xfz3xn6npa7k9e", "title": "富士康“回归”中国内地"}, {"url": "https://www.kuaishou.com/short-video/3x7qas46aws85cm", "title": "罗峰天才战一战成名"}, {"url": "https://www.kuaishou.com/short-video/3x46tpppb6zbndq", "title": "中国队荣登奥运奖牌榜第一"}, {"url": "https://www.kuaishou.com/short-video/3xsd4jc3stwd67s", "title": "当crush说看我跳舞不如看足球时"}, {"url": "https://www.kuaishou.com/short-video/3x9n7ph5iz6iuwa", "title": "挑战用楚新钓的方式在海南钓鱼"}, {"url": "https://www.kuaishou.com/short-video/3xyst6c93d5zite", "title": "徐嘉余妈妈和潘展乐爸爸同框"}]