[{"url": "https://www.kuaishou.com/short-video/3xqy9thiw8fhq26", "title": "深入推进数字中国建设"}, {"url": "https://www.kuaishou.com/short-video/3xeeuprcvgkctma", "title": "今日谷雨"}, {"url": "https://www.kuaishou.com/short-video/3x5qkkzbehf25nq", "title": "8名中国球员赴西特训"}, {"url": "https://www.kuaishou.com/short-video/3xvkz36kjbnyzhe", "title": "一组数字看2026开年的中国"}, {"url": "https://www.kuaishou.com/short-video/3x2tc7surpbmx32", "title": "2026年美国移民拘留17人死亡"}, {"url": "https://www.kuaishou.com/short-video/3xky4pgrnm5utka", "title": "梁家辉五封金像奖影帝"}, {"url": "https://www.kuaishou.com/short-video/3x82226swvxguxc", "title": "俏黄蓉离婚后首次接受采访"}, {"url": "https://www.kuaishou.com/short-video/3xarr8ywqasrkps", "title": "张雪机车荷兰站第二轮正赛"}, {"url": "https://www.kuaishou.com/short-video/3xxqt9967qipgbw", "title": "印度烟花厂爆炸16死"}, {"url": "https://www.kuaishou.com/short-video/3xx2exuhqc9rp7w", "title": "曝李小冉退出乘风2026"}, {"url": "https://www.kuaishou.com/short-video/3xanpfau2br5r7c", "title": "第44届金像奖获奖名单"}, {"url": "https://www.kuaishou.com/short-video/3x4mhsd7hvu6kk9", "title": "日本远程导弹射程已覆盖中国军港"}, {"url": "https://www.kuaishou.com/short-video/3xirksrfszqhpby", "title": "梁晶晶称流产5次失去7个孩子"}, {"url": "https://www.kuaishou.com/short-video/3xnep6pbc2ibpku", "title": "最近都在看什么剧"}, {"url": "https://www.kuaishou.com/short-video/3xqtts6uzzdsg34", "title": "咕咕嘎嘎"}, {"url": "https://www.kuaishou.com/short-video/3x487anvyn49ri4", "title": "福原爱三胎生子"}, {"url": "https://www.kuaishou.com/short-video/3xu7tryazg32ecs", "title": "谷雨这天一定别忘了洗澡"}, {"url": "https://www.kuaishou.com/short-video/3xsh5ru7nmvqtx2", "title": "时间出了张杀我没闪躲不掉"}, {"url": "https://www.kuaishou.com/short-video/3xu9ykrigj4k2pq", "title": "东京审判80周年奠定东亚秩序"}, {"url": "https://www.kuaishou.com/short-video/3xm5t7rcinhfyqe", "title": "雨过后的风景dj卡点舞"}, {"url": "https://www.kuaishou.com/short-video/3xfve52vnfufyey", "title": "长夜月cos"}, {"url": "https://www.kuaishou.com/short-video/3xh28ic7p85936c", "title": "南部沿海飞行员披露外军动态"}, {"url": "https://www.kuaishou.com/short-video/3xkchrszmij5sk6", "title": "火箭vs湖人"}, {"url": "https://www.kuaishou.com/short-video/3x8nnxeu5h7ppge", "title": "00后教师误闯天家"}, {"url": "https://www.kuaishou.com/short-video/3xvce8uabkqzfn6", "title": "男子自导自演反间谍戏码受处罚"}, {"url": "https://www.kuaishou.com/short-video/3xfq6xrsbggizu2", "title": "机器人摔倒后诡异抽搐"}, {"url": "https://www.kuaishou.com/short-video/3xqhjw7keaxrs5q", "title": "东部战区包头舰过航横当水道"}, {"url": "https://www.kuaishou.com/short-video/3xc2a8jd3s472ea", "title": "小姑娘为外卖员按电梯"}, {"url": "https://www.kuaishou.com/short-video/3x9rtk7sjngdhyw", "title": "中国肿瘤防治新突破"}, {"url": "https://www.kuaishou.com/short-video/3x8r3pcayqvxqt9", "title": "馨少摇来了"}, {"url": "https://www.kuaishou.com/short-video/3x6iup5mjcnw5r6", "title": "乌克兰称击中3艘俄军舰"}, {"url": "https://www.kuaishou.com/short-video/3xnttw48i6arz92", "title": "王虹获2026突破奖"}, {"url": "https://www.kuaishou.com/short-video/3xzf3kccwb66jra", "title": "马来西亚水上村庄大火千人受灾"}, {"url": "https://www.kuaishou.com/short-video/3xiazne8i74uqda", "title": "爱我你就抱抱我手势舞"}, {"url": "https://www.kuaishou.com/short-video/3xjvvy8bbpy7x2m", "title": "刘宇宁眼泪虽迟但到"}, {"url": "https://www.kuaishou.com/short-video/3xerzmidv8945z2", "title": "香港突发交通事故致多人受伤"}, {"url": "https://www.kuaishou.com/short-video/3x5emgyq5rgfkhm", "title": "我陈平安唯有一剑"}, {"url": "https://www.kuaishou.com/short-video/3xtwbvddvtvq78m", "title": "谷雨养生指南来了"}, {"url": "https://www.kuaishou.com/short-video/3xfy2iav4ep3f8m", "title": "中国布局太空采矿"}, {"url": "https://www.kuaishou.com/short-video/3xs3n54vibcxx89", "title": "劣质餐具锰含量超标"}, {"url": "https://www.kuaishou.com/short-video/3x7viqwch8iwdqg", "title": "今年谷雨适合播种吗"}, {"url": "https://www.kuaishou.com/short-video/3xtvwyhujsssa2a", "title": "我的心已经等你好多年"}, {"url": "https://www.kuaishou.com/short-video/3x7fkx6zytyry7k", "title": "15岁女孩选择跟后妈生活"}, {"url": "https://www.kuaishou.com/short-video/3x3eg2burd7vf7c", "title": "瓜果摇"}, {"url": "https://www.kuaishou.com/short-video/3xzx5tuscri9hrk", "title": "00后狙击甜妹火了"}, {"url": "https://www.kuaishou.com/short-video/3xzg3brqdz36shw", "title": "你想不想知道我当年啊"}, {"url": "https://www.kuaishou.com/short-video/3xrkmbsn2kn775u", "title": "谷雨节气的由来与传说"}, {"url": "https://www.kuaishou.com/short-video/3x3sczrm6cm3mbq", "title": "哒哒哒哒哒手势舞"}, {"url": "https://www.kuaishou.com/short-video/3xpqgp26n9bv5xg", "title": "你的酒馆对我打了烊"}, {"url": "https://www.kuaishou.com/short-video/3xtaukcepqraeju", "title": "宜昌一车辆爆燃现场多次爆炸"}, {"url": "https://www.kuaishou.com/short-video/3xymn3pcfx9jgs4", "title": "张雪儿子机车天赋超父亲"}, {"url": "https://www.kuaishou.com/short-video/3xpvxse6bhy3i2a", "title": "奥地利喜宝食品遭投毒勒索"}, {"url": "https://www.kuaishou.com/short-video/3xm9bxrid9qjyfy", "title": "张雪回应因性能太强遭限制"}, {"url": "https://www.kuaishou.com/short-video/3xxnp8zmghmwdx2", "title": "男子私房钱藏成小山"}, {"url": "https://www.kuaishou.com/short-video/3xvu3a9rf3ksyke", "title": "福建一车辆逆行撞人致2死1伤"}, {"url": "https://www.kuaishou.com/short-video/3xzwre455av2b7m", "title": "美国一跳伞运动员撞上记分牌"}, {"url": "https://www.kuaishou.com/short-video/3xdzzaep42s2v26", "title": "三月三机器人来广西也要跳竹竿舞"}, {"url": "https://www.kuaishou.com/short-video/3x5qtcbubm8aif9", "title": "谷雨是春天的最后一个节气"}, {"url": "https://www.kuaishou.com/short-video/3xxu6yzx8h8ga92", "title": "歼10C飞行训练太燃了"}, {"url": "https://www.kuaishou.com/short-video/3xn2q8bum2tqyz4", "title": "张雪骑820RR同看WSBK"}, {"url": "https://www.kuaishou.com/short-video/3xwt2z5nj65v9zs", "title": "南昌满城书香"}, {"url": "https://www.kuaishou.com/short-video/3xhx82fvwjt975e", "title": "柳州公安护航音浪之约"}, {"url": "https://www.kuaishou.com/short-video/3xwshfwpxwhz82i", "title": "WSBK荷兰站因车祸提前结束"}, {"url": "https://www.kuaishou.com/short-video/3xdjxnuwvf83dxc", "title": "张雪签名粉丝求合影"}, {"url": "https://www.kuaishou.com/short-video/3xd3hyu9pr3nx9s", "title": "谷雨是一年中最好的雨"}, {"url": "https://www.kuaishou.com/short-video/3xuptiiqnpab8q2", "title": "和平精英cos主角登场"}, {"url": "https://www.kuaishou.com/short-video/3xn659f3rbm4n3w", "title": "宿迁苏超第二现场沸腾"}, {"url": "https://www.kuaishou.com/short-video/3xcz4pah2ate3ti", "title": "白鹿把春天穿在身上"}, {"url": "https://www.kuaishou.com/short-video/3x8pcrg2mqjrq7s", "title": "李宁之星夺环岛赛第五冠"}, {"url": "https://www.kuaishou.com/short-video/3xwnhaagkgkvynu", "title": "接何润东事业运"}, {"url": "https://www.kuaishou.com/short-video/3xjit75hk2a53nw", "title": "马思纯回应亲密戏幕后"}, {"url": "https://www.kuaishou.com/short-video/3x2uv85ds7q5n2g", "title": "日本囤分离钚够造约5500枚核弹头"}, {"url": "https://www.kuaishou.com/short-video/3xjqawbguheswhw", "title": "刘兰芳每日阅读7小时"}, {"url": "https://www.kuaishou.com/short-video/3xgkxehxebrkp5u", "title": "吃不吃挑战"}, {"url": "https://www.kuaishou.com/short-video/3xhbvcya9qb5dbc", "title": "摩托摇"}, {"url": "https://www.kuaishou.com/short-video/3xb3hjfp9bfdez9", "title": "这是独属于中国人的国风底气"}, {"url": "https://www.kuaishou.com/short-video/3xzkstsbgjr8kmk", "title": "我真的特别爱你JK舞"}, {"url": "https://www.kuaishou.com/short-video/3xkqwzzc6p58z9k", "title": "娄艺潇南宁过三月三"}, {"url": "https://www.kuaishou.com/short-video/3xfr5wwi6gf6tiw", "title": "身高75厘米的最萌机器人来了"}, {"url": "https://www.kuaishou.com/short-video/3xxb6r4gvchxbwi", "title": "双人舞jk萌妹版"}, {"url": "https://www.kuaishou.com/short-video/3xyfmmuf7smr3xa", "title": "俏黄蓉逆袭重生收获百万粉丝"}, {"url": "https://www.kuaishou.com/short-video/3xy5x93uvfuckjm", "title": "你想不想知道我当年转场"}, {"url": "https://www.kuaishou.com/short-video/3xds4hs3fdn2ns6", "title": "小炮子放风筝又丢人了"}, {"url": "https://www.kuaishou.com/short-video/3xd25p27hqsumhe", "title": "贾翼瑄又来复仇了"}, {"url": "https://www.kuaishou.com/short-video/3xnsyfhz5z4ji4y", "title": "超自然行动组莉莉cos"}, {"url": "https://www.kuaishou.com/short-video/3x2yr2gnirxsj9w", "title": "龚琳娜南宁改编老友粉"}, {"url": "https://www.kuaishou.com/short-video/3xkxrwdwyzesrjy", "title": "北影节跨界对话创新玩法"}, {"url": "https://www.kuaishou.com/short-video/3xkai4csd9qtbx6", "title": "邓寓君南宁唱踏雪"}, {"url": "https://www.kuaishou.com/short-video/3xnq6hy6h7hmr8y", "title": "刘宇宁和粉丝大合唱"}, {"url": "https://www.kuaishou.com/short-video/3xy8ysxh94syks6", "title": "合肥马硕赵子宁散打夺冠"}, {"url": "https://www.kuaishou.com/short-video/3xceip4iczriw3y", "title": "快手亮相潍坊风筝节"}, {"url": "https://www.kuaishou.com/short-video/3x3v4ce4g2zze9m", "title": "黄奕谈何润东翻红"}, {"url": "https://www.kuaishou.com/short-video/3xmxerhqj4nm4dk", "title": "三月三拜轩辕"}, {"url": "https://www.kuaishou.com/short-video/3xc9wzcvkigthcw", "title": "杜华晒与雷军合照"}, {"url": "https://www.kuaishou.com/short-video/3xv9firfy4b2g8c", "title": "帮我配个BGM吧"}, {"url": "https://www.kuaishou.com/short-video/3xprnyqjq39viem", "title": "何润东参观项王故里"}, {"url": "https://www.kuaishou.com/short-video/3xkch3tach6zss4", "title": "当bro以为自己很有影响力时"}, {"url": "https://www.kuaishou.com/short-video/3xxkr4q4kiptckq", "title": "六小龄童呼和浩特签售新书"}]